Workbook

Sheet Log
A1: Date | B1: What I did | C1: How it developed the skill | D1: Referral category | E1: Referral area | F1: Competency | G1: Macro skill | H1: Age band | I1: Week | J1: Paste-ready line
A2: Rows 2 to 85 below are your Roscommon days, already filled in from Appendix 4. You only need the dropdowns in D to H. Rows after that are blank for Cavan.
A3: 46056 | B3: NEPS induction day. IT set-up. Expenses and service protocol briefing. 10:00-16:00 | J3: Day 1 · NEPS Head Office, Dublin
A4: 46057 | B4: Shadowed supervisor: parent interview, pupil interview, WISC-V and WIAT-III administration observed, parent feedback meeting. Supervision 16:00-17:00 | J4: Day 2 · Lisacul NS
A5: 46058 | B5: PENDING — preparation and case reading. Social Inclusion team meeting 14:30-15:30 (Teams) | J5: Day P1 · Remote
A6: 46059 | B6: Shadowed supervisor day 2: WISC-V, WIAT-III, parent interview. Supervision 15:00-17:00 | J6: Day 3 · Lisacul NS
A7: 46062 | B7: Shadowed colleague: case file review, parent interview, formulation discussion. NEPS Continuum of Support reading | J7: Day 4 · St Coman's Wood PS
A8: 46063 | B8: Shadowed colleague: WISC-V, WIAT-III, parent interview. Social Inclusion meeting 14:00-15:00 | J8: Day 5 · Cloonakilla NS, Athlone
A9: 46064 | B9: Shadowed colleague: WISC-V, WIAT-III administration and scoring, parent interview | J9: Day 6 · Scoil Mhuire (Newtown NS)
A10: 46065 | B10: WISC-V manual study: index score structure, ethical considerations in test use | J10: Day 7 · Remote
A11: 46069 | B11: WISC-V script notes, standardised administration rules, subtest practice | J11: Day 8 · Remote
A12: 46070 | B12: Observed WISC-V and WIAT-III, dyslexia query (CS25-05909); parent, teacher and student consultations. Whole-staff ADHD input to school | J12: Day 9 · S.N. Pol Naofa (St Paul's BNS)
A13: 46071 | B13: WISC-V subtest study (school half term) | J13: Day 10 · Remote
A14: 46072 | B14: Social Inclusion team meeting 10:00-12:30 (Teams). WISC-V subtest study | J14: Day 11 · Remote
... A86: 46212 | B86: Supervision (Teams) 14:00-15:00. Placement closing documentation | J86: Day 78 · Remote
J87: =IF($A87="","",TEXT($A87,"DD/MM/YYYY")&" — "&$B87&IF($E87="",""," [Referral: "&$E87&"]")&IF($G87="",""," [Competency: "&$G87&"]")&IF($C87="",""," How it developed the skill: "&$C87))
J88: =IF($A88="","",TEXT($A88,"DD/MM/YYYY")&" — "&$B88&IF($E88="",""," [Referral: "&$E88&"]")&IF($G88="",""," [Competency: "&$G88&"]")&IF($C88="",""," How it developed the skill: "&$C88))
J89: =IF($A89="","",TEXT($A89,"DD/MM/YYYY")&" — "&$B89&IF($E89="",""," [Referral: "&$E89&"]")&IF($G89="",""," [Competency: "&$G89&"]")&IF($C89="",""," How it developed the skill: "&$C89))
J90: =IF($A90="","",TEXT($A90,"DD/MM/YYYY")&" — "&$B90&IF($E90="",""," [Referral: "&$E90&"]")&IF($G90="",""," [Competency: "&$G90&"]")&IF($C90="",""," How it developed the skill: "&$C90))
J91: =IF($A91="","",TEXT($A91,"DD/MM/YYYY")&" — "&$B91&IF($E91="",""," [Referral: "&$E91&"]")&IF($G91="",""," [Competency: "&$G91&"]")&IF($C91="",""," How it developed the skill: "&$C91))
J92: =IF($A92="","",TEXT($A92,"DD/MM/YYYY")&" — "&$B92&IF($E92="",""," [Referral: "&$E92&"]")&IF($G92="",""," [Competency: "&$G92&"]")&IF($C92="",""," How it developed the skill: "&$C92))
J93: =IF($A93="","",TEXT($A93,"DD/MM/YYYY")&" — "&$B93&IF($E93="",""," [Referral: "&$E93&"]")&IF($G93="",""," [Competency: "&$G93&"]")&IF($C93="",""," How it developed the skill: "&$C93))
J94: =IF($A94="","",TEXT($A94,"DD/MM/YYYY")&" — "&$B94&IF($E94="",""," [Referral: "&$E94&"]")&IF($G94="",""," [Competency: "&$G94&"]")&IF($C94="",""," How it developed the skill: "&$C94))
J95: =IF($A95="","",TEXT($A95,"DD/MM/YYYY")&" — "&$B95&IF($E95="",""," [Referral: "&$E95&"]")&IF($G95="",""," [Competency: "&$G95&"]")&IF($C95="",""," How it developed the skill: "&$C95))
J96: =IF($A96="","",TEXT($A96,"DD/MM/YYYY")&" — "&$B96&IF($E96="",""," [Referral: "&$E96&"]")&IF($G96="",""," [Competency: "&$G96&"]")&IF($C96="",""," How it developed the skill: "&$C96))
J97: =IF($A97="","",TEXT($A97,"DD/MM/YYYY")&" — "&$B97&IF($E97="",""," [Referral: "&$E97&"]")&IF($G97="",""," [Competency: "&$G97&"]")&IF($C97="",""," How it developed the skill: "&$C97))
J98: =IF($A98="","",TEXT($A98,"DD/MM/YYYY")&" — "&$B98&IF($E98="",""," [Referral: "&$E98&"]")&IF($G98="",""," [Competency: "&$G98&"]")&IF($C98="",""," How it developed the skill: "&$C98))
... J402: =IF($A402="","",TEXT($A402,"DD/MM/YYYY")&" — "&$B402&IF($E402="",""," [Referral: "&$E402&"]")&IF($G402="",""," [Competency: "&$G402&"]")&IF($C402="",""," How it developed the skill: "&$C402))

Sheet Reference
A1: Level | B1: UCD competency | C1: Blocks within it | D1: Macro skill | E1: Section | F1: Item | G1: Detail / why it matters | H1: Law and policy | I1: Where the evidence goes | J1: Time · phase · type | K1: Times logged | L1: Last logged | M1: 1 | N1: 2 | O1: 3 | P1: 4 | Q1: 5 | R1: 6 | S1: 7 | T1: 8 | U1: 9 | V1: 10 | W1: 11 | X1: 12 | Y1: 13 | Z1: 14 | AA1: 15 | AB1: 16 | AC1: 17 | AD1: 18 | AE1: 19 | AF1: 20 | AG1: IFF · Environmental | AH1: IFF · Biological | AI1: IFF · Cognitive | AJ1: IFF · Affective | AK1: IFF · Behavioural
A2: INDEX | B2: JUMP TO | E2: Click any line. Use the 1 / 2 / 3 buttons in the left margin to collapse and expand: 1 = headings only, 2 = skill names, 3 = everything.
C3: 1. Assessment | E3: 10 macro skills | F3: teaching written for 10 of 10
C4: 2. Formulation | E4: 6 macro skills | F4: teaching written for 6 of 6
C5: 3. Intervention | E5: 7 macro skills | F5: teaching written for 7 of 7
C6: 4. Systemic Change | E6: 6 macro skills | F6: teaching written for 6 of 6
C7: 5. Working with Others | E7: 6 macro skills | F7: teaching written for 6 of 6
C8: 6. Ethical Practice | E8: 7 macro skills | F8: teaching written for 7 of 7
C9: 7. Supervision | E9: 10 macro skills | F9: teaching written for 10 of 10
C10: 8. Research | E10: 3 macro skills | F10: teaching written for 3 of 3
C11: PART D — age band → category → what presents → who they go to → what you assess | F11: the four-level route
C12: PART E — the three-year route to PSI membership and CORU registration | F12: shows where you do NOT currently meet a requirement
C13: PART F — papers behind the tool choices | F13: found through Elicit, clickable
C14: PART G — tool by tool, taught | F14: before · administer · score · interpret · errors · read
C15: PART H — methods in full, everything on one row | F15: history · evidence · script · Q&A · why this over alternatives
C16: PART I — conditions explained at parent, teacher and child level | F16: misconceptions · analogies · Q&A · supervision · reflection
C17: PART J — what is complete and what is not | F17: the honest map, with priority order
C18: PART C — Interactive Factors prompt, in full, with Irish equivalents | F18: also columns N to R — scroll right
C19: PART B — all 102 CORU standards and 128 PSI clauses in full | F19: every standard number in Part A links here
A25: PART A | B25: BY COMPETENCY | E25: One row per section. Columns A–L hold the context; the numbered columns to the right hold that section's items, spread across. Scroll right.
A26: COMP | B26: 1. Assessment | E26: 10 macro skills · 17 referral areas
B27: 1. Assessment | E27: What CORU asks of this competency — verbatim | F27: 18 standards across this competency | M27: ▸ CORU 1.2 Be able to identify the limits of their practice and know when to seek advice and additional expertise or refer to another professional | N27: ▸ CORU 2.2 Be able to modify and adapt communication methods and styles, including verbal and non-verbal methods, to suit the individual service user, considering issues of language, age, culture, beliefs and health and/or social care needs | O27: ▸ CORU 2.8 Be able to produce clear, concise, accurate and objective documentation | P27: ▸ CORU 3.1 Be able to gather all appropriate background information relevant to the service user's health and social care needs | Q27: ▸ CORU 3.2 Be able to justify the selection of and implement appropriate assessment techniques and be able to undertake and record a thorough, sensitive and detailed assessment | R27: ▸ CORU 3.3 Be able to determine the appropriate tests/assessments required and undertake/arrange these tests | S27: ▸ CORU 3.4 Be able to analyse and critically evaluate the information collected in the assessment process | T27: ▸ CORU 5.2 Demonstrate a critical understanding of relevant biological sciences, human development, social and behavioural sciences and other related sciences, together with a knowledge of health and wellbeing | U27: ▸ CORU 5.6 Demonstrate safe and effective implementation of practical, technical and clinical/professional skills | V27: ▸ CORU 5.12 Know the psychological theories of education, human development, learning and teaching and their application in children, young people and adult learners | W27: ▸ CORU 5.13 Know the structures and systems of school, community and social settings in which educational, health and social care services are provided for children, young people and adult learners | X27: ▸ CORU 5.14 Know the impact of structures and systems in which educational services are provided on the development of children, young people and adult learners at individual, group and organisational levels | Y27: ▸ CORU 5.21 Establish, maintain and conclude a professional relationship with a service user, safely and ethically, recognising and managing professional boundaries | Z27: ▸ CORU 5.24 Identify and apply knowledge of the intersecting forms of diversity of service users, working in an inclusive, sensitive and equitable manner | AA27: ▸ CORU 5.27 Be able to produce clear, concise, accessible and accurate reports — devised in collaboration with service users, as appropriate — that are suitable for the intended audience and context of their use, in order to communicate and justify professional opinions made | AB27: ▸ CORU 5.28 Be able to critically evaluate the theory and application of a range of assessment methods used in educational psychology to identify psychological, educational and developmental needs at individual and group levels | AC27: ▸ CORU 5.31 Conduct a range of assessment methods safely and ethically, adapting and re-evaluating their application as appropriate | AD27: ▸ CORU 5.32 Interpret, synthesise and critically evaluate assessment data, within relevant conceptual frameworks, to inform case formulation and psychological intervention planning
B28: 1. Assessment | E28: What the PSI Code asks of this competency — verbatim | F28: 13 clauses across this competency | M28: ▸ PSI 1.1.1 Have sensible regard for individual clients' moral and cultural values. | N28: ▸ PSI 1.1.3 Convey respect for and abide by prevailing community mores, social customs, and cultural expectations in their scientific and professional activities. | O28: ▸ PSI 1.3.5 Ensure at least the following are understood: purpose and nature of the activity; mutual responsibilities; likely benefits and risks; alternatives; consequences of non-action; the option to refuse or withdraw at any time without prejudice; the period the consent applies to; and how to rescind consent. | P28: ▸ PSI 1.4.1 Seek as full and active participation as possible from others in decisions which affect them. | Q28: ▸ PSI 1.4.3 Respect the right of individuals to discontinue participation or service at any time, and be responsive to non-verbal indications of a desire to discontinue. | R28: ▸ PSI 2.2.2 Recognise the boundaries of their competence, and do not exceed these. | S28: ▸ PSI 2.3.1 Be mindful, when making decisions based on psychological data and techniques, of the limitations of such data and techniques. | T28: ▸ PSI 2.3.3 Terminate an activity when it is clear the activity is more harmful than beneficial, or when it is no longer needed. | U28: ▸ PSI 3.3.6 Take all reasonable steps to ensure tests and assessment methods are only used by those qualified and trained to do so. | V28: ▸ PSI 4.2.2 Take due care to avoid misrepresentation, exaggeration, distortion or errors in reporting assessment results, research findings or service effectiveness, and act quickly to correct any such error. | W28: ▸ PSI 4.2.5 Take care in communicating their knowledge, findings and views to clearly differentiate facts, opinions, theories, hypotheses and ideas. | X28: ▸ PSI 4.2.6 Not suppress disconfirming evidence of their findings and views, and acknowledge alternative hypotheses and explanations. | Y28: ▸ PSI 4.3.1 Respect the right of clients and research participants to receive an appropriate explanation of the nature, purpose and results of investigations, assessments and research findings, in language they can understand.
B29: 1. Assessment | E29: Three-year arc | F29: What good looks like each year | M29: Year 1 — You learn the instruments and administer them to standard. Accuracy is the whole task. A good Year 1 assessment is one where another psychologist could re-score your protocol and reach the same numbers. | N29: Year 2 — You choose the battery rather than administering the one you were given. Selection becomes the skill, and you start assessing in health settings where the referral questions differ. | O29: Year 3 — You assess in complex and high-risk contexts, build cross-battery approaches deliberately, and can justify not assessing at all.
F30: one skill = one row → | M30: 1 · CORU — number and focus | N30: 2 · PSI — number and focus | O30: 3 · Why this matters | P30: 4 · Teaching — how you build it | Q30: 5 · What to read | R30: 6 · Common errors that cost marks | S30: 7 · Rubric — grade 3, 4, 5 | T30: 8 · Blocks and micro-skills with pass tests | U30: 9 · Full chapter, where written | V30: 10 · Referral areas this skill serves | W30: 11 · Where the evidence goes | X30: 12 · Law and policy | Y30: 13 · Year and how it extends | Z30: 14 · — | AA30: 15 · — | AB30: 16 · — | AC30: 17 · — | AD30: 18 · — | AE30: 19 · — | AF30: 20 · —
A31: SKILL | B31: 1. Assessment | C31: ▸ Knowing the methods ▸ Entering a setting ▸ Knowing what to look at ▸ Turning observation into data | D31: 1. Observation in classroom, playground and clinic | E31: Macro skill | F31: 1. Observation in classroom, playground and clinic | G31: Everything about this skill is on this row. Scroll right. | K31: =COUNTIF(Log!$G$3:$G$402,"1. Observation in classroom, playground and clinic") | L31: =IF(COUNTIF(Log!$G$3:$G$402,"1. Observation in classroom, playground and clinic")=0,"",SUMPRODUCT(MAX((Log!$G$3:$G$402="1. Observation in classroom, playground and clinic")*Log!$A$3:$A$402))) | M31: ▸ CORU 2.8 Be able to produce clear, concise, accurate and objective documentation ▸ CORU 3.1 Be able to gather all appropriate background information relevant to the service user's health and social care needs ▸ CORU 5.31 Conduct a range of assessment methods safely and ethically, adapting and re-evaluating their application as appropriate | N31: ▸ PSI 1.1.1 Have sensible regard for individual clients' moral and cultural values. ▸ PSI 2.2.2 Recognise the boundaries of their competence, and do not exceed these. ▸ PSI 2.3.1 Be mindful, when making decisions based on psychological data and techniques, of the limitations of such data and techniques. ▸ PSI 4.2.5 Take care in communicating their knowledge, findings and views to clearly differentiate facts, opinions, theories, hypotheses and ideas. | O31: Observation is the only assessment method that shows you the child in the environment the referral is actually about. A WISC-V tells you about a child in a quiet room with one adult and no competing demands — which is not where the difficulty is happening. Everything a teacher describes is mediated through their interpretation; observation is your one chance at unmediated data. It is also the method most often done badly, because it looks like something anyone can do. | P31: ▸ The four methods and what each is for Narrative (running record) — you write continuous prose about what happens. Strength: captures sequence and context you did not anticipate. Weakness: you cannot quantify it, and your attention drifts to what is salient rather than what is frequent. Use it first, when you do not yet know what you are looking for. Timed interval sampling — you divide the observation into fixed intervals (commonly 15 or 30 seconds) and record whether the behaviour occurred in each. Strength: gives you a percentage you can compare before and after an intervention. Weakness: tells you nothing about why. Use it when you need a baseline. Event sampling (frequency count) — you count each occurrence of a defined behaviour. Strength: exact counts for discrete, countable behaviours. Weakness: useless for continuous states like off-task. Use it for hitting, calling out, leaving the seat. ABC recording — for each occurrence you record what came immediately before (antecedent), the behaviour, and what followed (consequence). Strength: the only one of the four that generates a hypothesis about function. Weakness: slow, and you will miss things while writing. Use it when the referral question is why. ▸ Why the method must be chosen before you go If you arrive without a method you will default to narrative, and narrative confirms whatever you already believed. Choosing beforehand forces you to operationalise the behaviour — to turn 'disruptive' into something you could count. That operationalisation is half the assessment. If you cannot define the behaviour tightly enough to record it, the referral question is not yet clear, and that is worth discovering before you spend an hour in a classroom. ▸ Reactivity, and what to do about it Your presence changes behaviour. Children perform, or freeze, or seek your attention. This is not a flaw to eliminate but a variable to report. Two practical moves: stay long enough that novelty wears off (the first ten minutes are usually unrepresentative), and observe on more than one occasion where possible. In the report, say what you think your presence did. A sentence such as 'Over the first ten minutes the pupil looked towards me repeatedly; this reduced thereafter and the data below are drawn from the remaining period' is more credible than pretending you were invisible. ▸ Looking at the environment, not only the child The referral names a child, but the data you need is relational. Count how many times the teacher directs an instruction at this child compared with a peer. Note where the child is seated and what they can see. Note the transition points — most difficulties cluster at transitions rather than during tasks. If you leave with data only about the child, you have produced a within-child account by default, and your formulation will follow it. | Q31: ▸ Sharp, P., Frederickson, N., & Cline, T. (2015). Educational psychology in practice: Observation. In Frederickson & Cline, Special educational needs, inclusion and diversity (3rd ed.). Open University Press. — the chapter on assessment methods. ▸ Department of Education and Skills (2017). Continuum of Support: Guidelines for teachers. NEPS. — read the section on classroom support, so you know what you are observing against. ▸ CORU (2023). Standards of proficiency for educational psychologists. Standards 3.1, 3.2, 5.31. | R31: ✗ Recording interpretation as description — 'he was frustrated' is an inference; 'he pushed the worksheet away and put his head down' is an observation. Write the second and infer later. ✗ Observing only the target child, and producing a within-child formulation by accident. ✗ Generalising from one lesson. One maths lesson on a Friday afternoon is not a profile. ✗ Not agreeing an introduction, so the child is singled out or told something untrue. ✗ Choosing narrative every time because it requires no preparation. | S31: ▸ GRADE 3 You recorded what happened accurately but could not say why you chose that method. ▸ GRADE 4 Method chosen and applied correctly; description and interpretation separated; context recorded alongside the child. ▸ GRADE 5 You can name what your method was blind to, you observed across settings, and your observation answers the referral question rather than describing everything. | T31: ▸ BLOCK 1 · Knowing the methods [3–4 hours, once · Weeks 1–2 · Study] The four observation methods — timed interval, event sampling, ABC recording, narrative — and what each is good and bad at. How you build it: Read one methods chapter. Write a one-page comparison. Then use each once. · Choose a method suited to the referral question you have it when: You can say why this one and what another would have missed [CORU SoP 3.2] · Run a timed interval or event sample accurately you have it when: Intervals are consistent and the record is legible to someone else [CORU SoP 5.6] · Record antecedent, behaviour and consequence separately you have it when: You have not written the cause into the description [CORU SoP 2.8] ▸ BLOCK 2 · Entering a setting [1 hour, then practice · Weeks 3–6 · Practice] How to be in a classroom without becoming the event — introduction, positioning, presence. How you build it: Ask your supervisor how they introduce themselves. Copy it until you have your own. · Agree with the teacher how you will be introduced you have it when: The child is told something true and is not singled out [CORU SoP 1.5 · PSI Code 1.1.1] · Position yourself to see without becoming the focus you have it when: The class settles within a few minutes [CORU SoP 5.31] · Observe without altering what you came to see you have it when: You can name how your presence may have changed things [PSI Code 2.3.1] ▸ BLOCK 3 · Knowing what to look at [Builds over 5–6 observations · Weeks 3–6 · Practice] The things worth noticing beyond the target behaviour — peer positioning, adult prompting, task demand, transitions. How you build it: Observe one child for the referral question, then observe the same lesson again for the context. The second is where the learning is. · Note peer interaction and social positioning you have it when: You can describe where this child sits in the peer group [CORU SoP 5.16] · Note adult interaction and prompting patterns you have it when: You have characterised the level of support given [CORU SoP 5.14] · Observe the same child across two settings you have it when: You have not generalised from one lesson [CORU SoP 3.1] ▸ BLOCK 4 · Turning observation into data [2–3 hours, then habit · Weeks 3–6 · Habit] Keeping description separate from interpretation, and linking what you saw to the question you were asked. How you build it: Write both sections separately for five observations. Have one checked. · Keep description and interpretation separate you have it when: Opinion is labelled as opinion throughout [CORU SoP 2.8 · PSI Code 4.2.5] · Link what you observed to the referral question you have it when: The observation answers something rather than describing everything [CORU SoP 3.4] | U31: ▸ Stage 1 · 0–25% What observation is actually for An observation answers a question that scores cannot. Scores tell you what a child can do under standardised, one-to-one, low-distraction conditions with an adult whose whole attention is on them. That is not a classroom. Observation tells you what the child does in the place where the difficulty was reported, which is almost always where the intervention will have to work. Description is not interpretation, and the whole discipline rests on keeping them apart. "Pushed the worksheet away" is description. "Was frustrated" is interpretation. "Avoids tasks he finds difficult" is a hypothesis. Write only the first in the observation record. The second belongs in the formulation, where you can be challenged on it. Trainees blur these constantly and it is the single most common reason an observation record is worthless to anyone else. Reactivity. Your presence changes the classroom. The teacher gives more directions, the target child either performs or freezes, the class watches you. This is not a flaw you can eliminate, only one you can reduce and report. Reduce it by staying longer than you need, sitting where you are not in sightlines, and agreeing a neutral introduction with the teacher beforehand. Report it by saying in the report that you observed for X minutes on one occasion and that your presence may have affected what you saw. What observation cannot tell you. It cannot tell you why. It can tell you what happens, how often, what comes before and after, and how this child compares to a peer in the same room. Causation requires either a functional analysis in which you manipulate conditions, or convergence with other evidence. A single observation is a snapshot with an n of one. ▸ Stage 2 · 25–50% Every method, and what each one is for There are seven methods you will actually use. Choosing between them before you enter the room is the skill; most trainees default to narrative because it requires no decision, and then find they have pages of prose that answer nothing. MethodWhat you doUse it whenWhat it cannot tell you Narrative / running recordWrite continuously in plain language, in sequence, with timestamps every few minutes.You do not yet know what the problem is. First observation of a new referral.Frequency, duration, or comparison. It is descriptive only and does not produce data. Event / frequency samplingTally each occurrence of a defined behaviour. Define it tightly first — "calls out without hand up" not "disruptive".The behaviour is discrete, countable, and has a clear start and end.How long each episode lasts, or what triggered it. Duration recordingTime each episode with a stopwatch, from a defined start to a defined end.How long matters more than how often — time off task, time to settle after transition.Frequency patterns, or context. Whole-interval recordingDivide the period into intervals (say 15 seconds). Mark only if the behaviour occurred for the entire interval.Continuous behaviours you want to be conservative about — on-task engagement.It systematically underestimates. Known bias; say so. Partial-interval recordingMark if the behaviour occurred at any point in the interval.Brief or high-frequency behaviours that are hard to count individually.It systematically overestimates. Known bias; say so. Momentary time samplingAt the end of each interval, look up and record whether the behaviour is occurring at that instant.You need an unbiased estimate of how much of the time something occurs, and you want to observe other things in between.Anything about individual episodes. But it is the least biased of the three interval methods and the one to prefer for engagement. ABC recordingThree columns. Antecedent, behaviour, consequence. Fill all three for every episode, in the moment.You are building a hypothesis about function.Function itself. ABC is descriptive functional assessment, not experimental. It generates a hypothesis; it does not confirm one. The comparison peer. An observation of a target child alone is nearly uninterpretable, because you have no idea what normal looks like in that room. Pick a same-sex peer of average attainment sitting in a comparable position, and record them on the same schedule. "Target child off task 60% of intervals" means nothing. "Target child off task 60%, comparison peer 25%" is a finding. ▸ Stage 3 · 50–75% Making it defensible Operational definitions. Before you observe, write down what counts. "Off task" must specify: not looking at the work, the teacher, or a peer who is helping, for more than three consecutive seconds. If you cannot write the definition, you cannot record the behaviour reliably, and neither can anyone else. Inter-observer agreement. The standard check is to have a second observer record simultaneously and compute agreement. Simple percentage agreement is agreements divided by agreements plus disagreements; Cohen's kappa corrects for chance agreement and is the better statistic. You will rarely get a second observer on placement. The honest response is to say so in the report rather than to imply a reliability you did not establish. Sampling adequacy. One twenty-minute observation in one lesson on one day is a very small sample of a child's week. Two settings minimum, and where you only have one, write in the report that one lesson is what you have. Vary time of day if you can — behaviour before lunch and after lunch are not the same behaviour. Scheduling. Choose the lesson where the difficulty was reported, not the lesson that is convenient. If the referral is about literacy, observing PE tells you something but not the thing you were asked. ▸ Stage 4 · 75–100% What experts know that the training does not say The psychometrics of classroom observation are weaker than practice assumes. Systematic direct observation has reasonable inter-observer reliability when definitions are tight, but temporal stability is poor — the same child observed on two different days can produce substantially different rates. Published work on observation of classroom behaviour has repeatedly found that a single session is an unreliable estimate of a child's typical behaviour, and that several sessions are needed for a stable estimate. Practising psychologists routinely report a single observation as though it were stable. Know that this is a compromise, and report the number of sessions. Observer expectancy. You read the referral before you observe. That referral tells you what to look for, and you will find it. This is not carelessness; it is a well-documented effect. Mitigations: define behaviours before reading the referral where possible; record the comparison peer on the same schedule so your bias applies equally to both; record descriptively and interpret afterwards rather than in the room. Descriptive versus experimental functional assessment. ABC recording is descriptive — you watch what naturally happens. Experimental functional analysis manipulates conditions systematically to test function. Descriptive methods agree with experimental methods less often than practitioners assume, particularly for behaviours maintained by automatic reinforcement. An ABC record supports a hypothesis; it does not establish a function. Write "consistent with" rather than "the function of this behaviour is". Structured protocols exist and are mostly better than what you will invent. The BOSS (Behavioral Observation of Students in Schools) uses momentary time sampling with a built-in peer comparison. The Student Behavior Teacher Response and similar coded systems capture the interaction rather than the child alone. Using a published protocol gives you a defined behaviour set and an evidence base; inventing your own each time gives you neither. When not to observe. If the referral question is about attainment rather than behaviour, observation adds little. If the child knows why you are there and is old enough to perform, the observation may be worse than useless. And if the teacher has already given you a clear behavioural account with frequencies, your observation may only confirm it at the cost of a morning. ▸ What to read SourceRead it for Sattler, J. M. (2018). Assessment of children: Cognitive foundations (6th ed.). Sattler Publisher.The observation chapter. The most practical single treatment of the methods. Frederickson, N., & Cline, T. (2015). Special educational needs, inclusion and diversity (3rd ed.). Open University Press.Observation within an ecological and interactive frame, written for UK/Irish EP practice. Shapiro, E. S. (2011). Academic skills problems workbook (4th ed.). Guilford.The BOSS protocol and how peer comparison is built into it. Hintze, J. M. (2005). Psychometrics of direct observation. School Psychology Review, 34(4), 507–519.The reliability and stability problem, stated directly. This is the stage-four reading. Thompson, R. H., & Iwata, B. A. (2007). A comparison of outcomes from descriptive and functional analyses of problem behavior. Journal of Applied Behavior Analysis, 40(2), 333–338.Why ABC and experimental functional analysis disagree. ▸ Copy and paste Click any block to copy it. Operational definition sheet Behaviour · Counts as · Does not count as · Minimum duration · Method · Interval · Comparison peer · Settings · Date ABC recording grid Time · Antecedent · Behaviour · Consequence, with the descriptive-only caveat built in Momentary time sampling grid, with peer comparison 20 intervals, target and comparison peer on the same schedule Observation write-up paragraph Method, definition, peer comparison, findings, and the limitations sentence that moves a report from a 3 to a 5 | V31: ▸ 1.1 Attention, concentration and work skills FULL ENTRY HERE ▸ 1.2 Language skills FULL ENTRY HERE ▸ 1.6 Co-ordination — fine motor / handwriting, gross motor / PE skills FULL ENTRY HERE ▸ 2.1 Behaviour in class FULL ENTRY HERE ▸ 2.2 Behaviour during break times and around the school FULL ENTRY HERE ▸ 4.1 Friendships and social skills full entry under 8. Social communication screening measures | W31: Table 2 area 1 · Appendix 5 tagged Assessment · Appendix 7 observation · Table 3 tools and categories | X31: Equal Status Acts 2000–2018 — reasonable accommodation · GDPR — lawful basis, minimisation | Y31: Year 1 — Extends to health and disability settings in Year 2.
A32: AREA | B32: 1. Assessment | D32: 1. Observation in classroom, playground and clinic | E32: Referral area | F32: 1.1 Attention, concentration and work skills | G32: ON THE FORM — Section 5 | K32: =COUNTIF(Log!$E$3:$E$402,"1.1 Attention, concentration and work skills") | L32: =IF(COUNTIF(Log!$E$3:$E$402,"1.1 Attention, concentration and work skills")=0,"",SUMPRODUCT(MAX((Log!$E$3:$E$402="1.1 Attention, concentration and work skills")*Log!$A$3:$A$402))) | M32: DIAGNOSES ▸ ADHD — combined presentation DSM-5-TR / ICD-11 6A05 ▸ ADHD — predominantly inattentive presentation DSM-5-TR / ICD-11 6A05 ▸ ADHD — predominantly hyperactive/impulsive presentation DSM-5-TR / ICD-11 6A05 ▸ Other specified ADHD DSM-5-TR / ICD-11 6A05 ▸ Unspecified ADHD DSM-5-TR / ICD-11 6A05 | N32: PRESENTATIONS WITH NO DIAGNOSIS ▸ Working memory difficulty Executive function profile, not a diagnosis ▸ Inhibition difficulty Executive function profile ▸ Cognitive flexibility difficulty Executive function profile ▸ Planning and organisation difficulty Executive function profile ▸ Task initiation difficulty Executive function profile ▸ Self-monitoring difficulty Executive function profile ▸ Motivation and engagement with work Added — not in the conditions index ▸ Work rate and pace of output Added ▸ Homework completion and follow-through Added ▸ Organisation of materials, books and equipment Added ▸ Sustained attention in whole-class vs one-to-one Added ▸ Note-taking and recording from the board Added ▸ Study skills and revision strategy Added ▸ Help-seeking — knowing when and how to ask Added ▸ Fatigue, sleep and time-of-day effects on attention Added | O32: REFER TO ▸ CAMHS (complex or medication) ▸ Primary Care ▸ CAMHS ▸ NEPS ▸ GP if persistent | P32: — | Q32: ▸ Early Years / Pre-School (0–5) Structured play observation · developmental history with parent · Preschool/AIM staff consultation · Conners EC (3–6) · no standardised cognitive attention measure at this age — describe, do not score. | R32: ▸ School Age (6–12) Classroom observation (momentary time sampling with a comparison peer) · Conners-4 parent and teacher · BRIEF-2 parent and teacher · WISC-V Working Memory and Processing Speed indices · TEA-Ch2 · work-sample analysis. | S32: ▸ Adolescent (13–16) Conners-4 including self-report · BRIEF-2 self-report · WISC-V or WAIS-IV depending on age · subject-teacher survey (Form 2 page 8) · study-skills and homework interview · RACE evidence if exam access is in question. | T32: ▸ Young Adult (17–26) WAIS-IV · BRIEF-A · self-report interview on study and workload · DSA/reasonable-accommodation evidence for third level · workplace or course demands analysis. | U32: ▸ Special Setting (class or school) Same tools, but interpret against the setting norm rather than the mainstream norm · staff consultation on the support already in place · check the referral question is about the pupil and not the placement. | AG32: Environmental Factors — Family, School, Community · Family dynamics (including CEC, adopted and CYP with SGOs) · Siblings, extended family, links and relationship to school and education · Family stressors · Financial stress · Housing · Home learning environment · Parental attitude to school/education · Trauma/significant life events · Adverse childhood events · Family views · Bereavements/relational losses · Key adults / members of staff (significant relationships both positive and negative in and out of school) and level of school commitment to child · Travel distance to school · School attendance · Child's views/preferences · School-parent relationship · Peer group dynamics · School learning environment · Access to interventions and support · Curriculum/exam boards · Teacher expectations · Teacher/staff understanding/knowledge · Attainment-based grouping · Influences in school and the local community · Other agency involvement — Police, YOT, CAMHS, Speech and Language Service, Fair Access, SENAT, Virtual School, SGO Advisor, Intensive Planning Team, Prevent, CSE, Early Years, School Nurse, Portage, Early Help, Social and Caring Services Health Services | AH32: Within-Child — Biological Factors · Family history including early development, physical development, medical conditions and diagnoses/difficulties · General health · Medication · Dietary needs · Sensory needs · Addictions e.g. smoking, drink, drugs | AI32: Within-Child — Cognitive Factors ASSESSABLE · Memory · Language · Executive functioning: including emotional and behavioural regulation/development · Attention and concentration · Visual spatial ability · Phonological processing · Processing speed · Non-verbal reasoning · Verbal ability (e.g. word problems, verbal presentation) · Logical reasoning ability · Literacy skills · Attainment OBSERVATION AND CONSULTATION · Signs of developmental trauma impacting on ability to participate in learning · Ability to problem-solve · Flexibility of thought and action · Self-awareness | AJ32: Within-Child — Affective Factors · Experience of developmental trauma · Confidence · Self-esteem · Emotional understanding and expression · Sense of enablement · Sense of self · Sense of belonging · Motivation (intrinsic or extrinsic) · Resiliency · Mood · Anxiety · Aspirations · Perseverance / determination · Sense of humour · Self-control · Social skills · Empathy | AK32: Within-Child — Behavioural Factors · Ability to develop and maintain friendships and relationships · Positive achievements · Care/concern for others, volunteering, helping · Dangerous or risk-taking behaviour · Verbal / physical abuse · Self-harm · Bullying · Truancy
A33: AREA | B33: 1. Assessment | D33: 1. Observation in classroom, playground and clinic | E33: Referral area | F33: 1.2 Language skills | G33: ON THE FORM — Section 5 | K33: =COUNTIF(Log!$E$3:$E$402,"1.2 Language skills") | L33: =IF(COUNTIF(Log!$E$3:$E$402,"1.2 Language skills")=0,"",SUMPRODUCT(MAX((Log!$E$3:$E$402="1.2 Language skills")*Log!$A$3:$A$402))) | M33: DIAGNOSES ▸ Language Disorder (expressive / receptive / mixed) — DLD DSM-5-TR / ICD-11 6A01 ▸ Speech Sound Disorder DSM-5-TR / ICD-11 6A01 ▸ Childhood-Onset Fluency Disorder (stuttering) DSM-5-TR / ICD-11 6A01 ▸ Unspecified Communication Disorder DSM-5-TR / ICD-11 6A01 ▸ Selective mutism DSM-5-TR anxiety / ICD-11 6B00–6B0Z | N33: PRESENTATIONS WITH NO DIAGNOSIS ▸ AAC and communication access Not a DSM diagnosis ▸ English as an Additional Language (EAL) Not a disorder — can mimic language disorder, rule out ▸ Bilingual language development Not a disorder ▸ Vocabulary gap from limited exposure Added ▸ Participation in oral work and classroom talk Added — Form 2 wording ▸ Following multi-step verbal instructions Added ▸ Narrative and sequencing in spoken account Added ▸ Word-finding difficulty Added ▸ Interpreter need and how it changes the assessment Added | O33: REFER TO ▸ NEPS with SLT ▸ NCSE speech and language class ▸ Primary Care (mild–moderate) ▸ CAMHS (severe) — also under 3.2 ▸ SLT ▸ CDNT ▸ NEPS ▸ NEPS interpreter request form | P33: — | Q33: ▸ Early Years / Pre-School (0–5) Preschool SLT report if any · parent developmental history (first words, phrases) · play-based language sample · Preschool Language Scales · always establish home language exposure before interpreting. | R33: ▸ School Age (6–12) BPVS-3 receptive vocabulary · EVT-3 expressive · CELF-5 via SLT · WISC-V Verbal Comprehension Index · classroom observation of oral participation · teacher report on instruction-following. | S33: ▸ Adolescent (13–16) CELF-5 (up to 21) via SLT · WISC-V/WAIS-IV VCI · subject-teacher survey on oral response · self-report on being understood · consider literacy consequences of unresolved DLD. | T33: ▸ Young Adult (17–26) WAIS-IV VCI · functional communication interview · course or workplace demands · self-advocacy for communication access. | U33: ▸ Special Setting (class or school) Language level of the setting itself · staff consultation on total communication approach · AAC in use and whether it is being used consistently. | AG33: Environmental Factors — Family, School, Community · Family dynamics (including CEC, adopted and CYP with SGOs) · Siblings, extended family, links and relationship to school and education · Family stressors · Financial stress · Housing · Home learning environment · Parental attitude to school/education · Trauma/significant life events · Adverse childhood events · Family views · Bereavements/relational losses · Key adults / members of staff (significant relationships both positive and negative in and out of school) and level of school commitment to child · Travel distance to school · School attendance · Child's views/preferences · School-parent relationship · Peer group dynamics · School learning environment · Access to interventions and support · Curriculum/exam boards · Teacher expectations · Teacher/staff understanding/knowledge · Attainment-based grouping · Influences in school and the local community · Other agency involvement — Police, YOT, CAMHS, Speech and Language Service, Fair Access, SENAT, Virtual School, SGO Advisor, Intensive Planning Team, Prevent, CSE, Early Years, School Nurse, Portage, Early Help, Social and Caring Services Health Services | AH33: Within-Child — Biological Factors · Family history including early development, physical development, medical conditions and diagnoses/difficulties · General health · Medication · Dietary needs · Sensory needs · Addictions e.g. smoking, drink, drugs | AI33: Within-Child — Cognitive Factors ASSESSABLE · Memory · Language · Executive functioning: including emotional and behavioural regulation/development · Attention and concentration · Visual spatial ability · Phonological processing · Processing speed · Non-verbal reasoning · Verbal ability (e.g. word problems, verbal presentation) · Logical reasoning ability · Literacy skills · Attainment OBSERVATION AND CONSULTATION · Signs of developmental trauma impacting on ability to participate in learning · Ability to problem-solve · Flexibility of thought and action · Self-awareness | AJ33: Within-Child — Affective Factors · Experience of developmental trauma · Confidence · Self-esteem · Emotional understanding and expression · Sense of enablement · Sense of self · Sense of belonging · Motivation (intrinsic or extrinsic) · Resiliency · Mood · Anxiety · Aspirations · Perseverance / determination · Sense of humour · Self-control · Social skills · Empathy | AK33: Within-Child — Behavioural Factors · Ability to develop and maintain friendships and relationships · Positive achievements · Care/concern for others, volunteering, helping · Dangerous or risk-taking behaviour · Verbal / physical abuse · Self-harm · Bullying · Truancy
A34: AREA | B34: 1. Assessment | D34: 1. Observation in classroom, playground and clinic | E34: Referral area | F34: 1.6 Co-ordination — fine motor / handwriting, gross motor / PE skills | G34: ON THE FORM — Section 5 | K34: =COUNTIF(Log!$E$3:$E$402,"1.6 Co-ordination — fine motor / handwriting, gross motor / PE skills") | L34: =IF(COUNTIF(Log!$E$3:$E$402,"1.6 Co-ordination — fine motor / handwriting, gross motor / PE skills")=0,"",SUMPRODUCT(MAX((Log!$E$3:$E$402="1.6 Co-ordination — fine motor / handwriting, gross motor / PE skills")*Log!$A$3:$A$402))) | M34: DIAGNOSES ▸ Developmental Coordination Disorder (dyspraxia) DSM-5-TR / ICD-11 6A04 ▸ Stereotypic Movement Disorder DSM-5-TR / ICD-11 6A04 ▸ Tourette's Disorder DSM-5-TR / ICD-11 Ch.08 ▸ Persistent (chronic) motor or vocal tic disorder DSM-5-TR / ICD-11 Ch.08 ▸ Provisional tic disorder DSM-5-TR / ICD-11 Ch.08 ▸ Other specified / unspecified tic disorder DSM-5-TR / ICD-11 Ch.08 ▸ Hypermobility spectrum disorder Medical | N34: PRESENTATIONS WITH NO DIAGNOSIS ▸ Fine motor difficulty (handwriting, pencil grip) Not a DSM diagnosis ▸ Gross motor difficulty (PE, balance, ball skills) Not a DSM diagnosis ▸ Sensory modulation difficulties (over- or under-responsive) Not a DSM diagnosis ▸ Sensory discrimination difficulties Not a DSM diagnosis ▸ Motor-based sensory difficulties Not a DSM diagnosis ▸ Presentation and care of written work Added — Form 2 wording ▸ Self-care and independence skills at school Added | O34: REFER TO ▸ CDNT / Occupational Therapy ▸ CDNT / OT ▸ CAMHS ▸ GP ▸ Paediatrics ▸ Occupational Therapy ▸ OT ▸ Physiotherapy ▸ NEPS | P34: — | Q34: ▸ Early Years / Pre-School (0–5) Movement ABC-2 (3+) · parent report on dressing, feeding, stairs · preschool observation · OT referral is usually the pathway, not NEPS assessment. | R34: ▸ School Age (6–12) DCD-Q parent questionnaire · Movement ABC-2 · Beery VMI · DASH handwriting speed · classroom observation of writing posture and grip · OT for diagnosis. | S34: ▸ Adolescent (13–16) DASH · Beery VMI · self-report on PE avoidance and social impact · RACE for handwriting (word processor, scribe) · practical-subject demands. | T34: ▸ Young Adult (17–26) DASH-17+ · functional and workplace demands · driving, laboratory or practical course requirements. | U34: ▸ Special Setting (class or school) Access to the physical environment · equipment and seating in place · OT recommendations already implemented or not. | AG34: Environmental Factors — Family, School, Community · Family dynamics (including CEC, adopted and CYP with SGOs) · Siblings, extended family, links and relationship to school and education · Family stressors · Financial stress · Housing · Home learning environment · Parental attitude to school/education · Trauma/significant life events · Adverse childhood events · Family views · Bereavements/relational losses · Key adults / members of staff (significant relationships both positive and negative in and out of school) and level of school commitment to child · Travel distance to school · School attendance · Child's views/preferences · School-parent relationship · Peer group dynamics · School learning environment · Access to interventions and support · Curriculum/exam boards · Teacher expectations · Teacher/staff understanding/knowledge · Attainment-based grouping · Influences in school and the local community · Other agency involvement — Police, YOT, CAMHS, Speech and Language Service, Fair Access, SENAT, Virtual School, SGO Advisor, Intensive Planning Team, Prevent, CSE, Early Years, School Nurse, Portage, Early Help, Social and Caring Services Health Services | AH34: Within-Child — Biological Factors · Family history including early development, physical development, medical conditions and diagnoses/difficulties · General health · Medication · Dietary needs · Sensory needs · Addictions e.g. smoking, drink, drugs | AI34: Within-Child — Cognitive Factors ASSESSABLE · Memory · Language · Executive functioning: including emotional and behavioural regulation/development · Attention and concentration · Visual spatial ability · Phonological processing · Processing speed · Non-verbal reasoning · Verbal ability (e.g. word problems, verbal presentation) · Logical reasoning ability · Literacy skills · Attainment OBSERVATION AND CONSULTATION · Signs of developmental trauma impacting on ability to participate in learning · Ability to problem-solve · Flexibility of thought and action · Self-awareness | AJ34: Within-Child — Affective Factors · Experience of developmental trauma · Confidence · Self-esteem · Emotional understanding and expression · Sense of enablement · Sense of self · Sense of belonging · Motivation (intrinsic or extrinsic) · Resiliency · Mood · Anxiety · Aspirations · Perseverance / determination · Sense of humour · Self-control · Social skills · Empathy | AK34: Within-Child — Behavioural Factors · Ability to develop and maintain friendships and relationships · Positive achievements · Care/concern for others, volunteering, helping · Dangerous or risk-taking behaviour · Verbal / physical abuse · Self-harm · Bullying · Truancy
A35: AREA | B35: 1. Assessment | D35: 1. Observation in classroom, playground and clinic | E35: Referral area | F35: 2.1 Behaviour in class | G35: ON THE FORM — Section 5 | K35: =COUNTIF(Log!$E$3:$E$402,"2.1 Behaviour in class") | L35: =IF(COUNTIF(Log!$E$3:$E$402,"2.1 Behaviour in class")=0,"",SUMPRODUCT(MAX((Log!$E$3:$E$402="2.1 Behaviour in class")*Log!$A$3:$A$402))) | M35: DIAGNOSES ▸ Oppositional Defiant Disorder — mild DSM-5-TR / ICD-11 6C90–6C9Z ▸ Oppositional Defiant Disorder — moderate DSM-5-TR / ICD-11 6C90–6C9Z ▸ Oppositional Defiant Disorder — severe DSM-5-TR / ICD-11 6C90–6C9Z ▸ Intermittent Explosive Disorder DSM-5-TR / ICD-11 6C70–6C7Z ▸ Disruptive Mood Dysregulation Disorder DSM-5-TR / ICD-11 6A70–6A7Z | N35: PRESENTATIONS WITH NO DIAGNOSIS ▸ Behaviour that challenges Not a DSM diagnosis ▸ Behaviour function (ABC analysis, trigger-behaviour-consequence) Formulation approach, not a diagnosis ▸ Emotion regulation in the classroom Added ▸ Response to correction and repair after an incident Added ▸ Transitions between activities and between classes Added ▸ Behaviour system fit — is the system working for this pupil Added ▸ Escalation and de-escalation pattern Added ▸ Behaviour as communication of an unmet learning need Added — always test this hypothesis | O35: REFER TO ▸ NEPS (school behaviour) ▸ CAMHS ▸ NEPS ▸ CAMHS (mod–severe) ▸ Primary Care (mild–mod) | P35: — | Q35: ▸ Early Years / Pre-School (0–5) ABC recording by preschool staff · structured observation · parent report on home/setting difference · SDQ (2–4 version) · behaviour at this age is usually developmental — frame it that way. | R35: ▸ School Age (6–12) ABC grid across a week · momentary time sampling with peer comparison · SDQ or BASC-3 (TRS and PRS) · functional behaviour assessment · Continuum of Support level check. | S35: ▸ Adolescent (13–16) BASC-3 including self-report · subject-teacher survey — is it all classes or some · pupil interview on their account of the incidents · school discipline record. | T35: ▸ Young Adult (17–26) Self-report and functional analysis · course or workplace conduct expectations · less likely to be a NEPS referral. | U35: ▸ Special Setting (class or school) Behaviour against the setting baseline · staff consistency · whether the environment is generating the behaviour. | AG35: Environmental Factors — Family, School, Community · Family dynamics (including CEC, adopted and CYP with SGOs) · Siblings, extended family, links and relationship to school and education · Family stressors · Financial stress · Housing · Home learning environment · Parental attitude to school/education · Trauma/significant life events · Adverse childhood events · Family views · Bereavements/relational losses · Key adults / members of staff (significant relationships both positive and negative in and out of school) and level of school commitment to child · Travel distance to school · School attendance · Child's views/preferences · School-parent relationship · Peer group dynamics · School learning environment · Access to interventions and support · Curriculum/exam boards · Teacher expectations · Teacher/staff understanding/knowledge · Attainment-based grouping · Influences in school and the local community · Other agency involvement — Police, YOT, CAMHS, Speech and Language Service, Fair Access, SENAT, Virtual School, SGO Advisor, Intensive Planning Team, Prevent, CSE, Early Years, School Nurse, Portage, Early Help, Social and Caring Services Health Services | AH35: Within-Child — Biological Factors · Family history including early development, physical development, medical conditions and diagnoses/difficulties · General health · Medication · Dietary needs · Sensory needs · Addictions e.g. smoking, drink, drugs | AI35: Within-Child — Cognitive Factors ASSESSABLE · Memory · Language · Executive functioning: including emotional and behavioural regulation/development · Attention and concentration · Visual spatial ability · Phonological processing · Processing speed · Non-verbal reasoning · Verbal ability (e.g. word problems, verbal presentation) · Logical reasoning ability · Literacy skills · Attainment OBSERVATION AND CONSULTATION · Signs of developmental trauma impacting on ability to participate in learning · Ability to problem-solve · Flexibility of thought and action · Self-awareness | AJ35: Within-Child — Affective Factors · Experience of developmental trauma · Confidence · Self-esteem · Emotional understanding and expression · Sense of enablement · Sense of self · Sense of belonging · Motivation (intrinsic or extrinsic) · Resiliency · Mood · Anxiety · Aspirations · Perseverance / determination · Sense of humour · Self-control · Social skills · Empathy | AK35: Within-Child — Behavioural Factors · Ability to develop and maintain friendships and relationships · Positive achievements · Care/concern for others, volunteering, helping · Dangerous or risk-taking behaviour · Verbal / physical abuse · Self-harm · Bullying · Truancy
A36: AREA | B36: 1. Assessment | D36: 1. Observation in classroom, playground and clinic | E36: Referral area | F36: 2.2 Behaviour during break times and around the school | G36: ON THE FORM — Section 5 | K36: =COUNTIF(Log!$E$3:$E$402,"2.2 Behaviour during break times and around the school") | L36: =IF(COUNTIF(Log!$E$3:$E$402,"2.2 Behaviour during break times and around the school")=0,"",SUMPRODUCT(MAX((Log!$E$3:$E$402="2.2 Behaviour during break times and around the school")*Log!$A$3:$A$402))) | M36: DIAGNOSES ▸ Conduct Disorder — childhood-onset type DSM-5-TR / ICD-11 6C90–6C9Z ▸ Conduct Disorder — adolescent-onset type DSM-5-TR / ICD-11 6C90–6C9Z ▸ Conduct Disorder — unspecified onset DSM-5-TR / ICD-11 6C90–6C9Z ▸ Pyromania DSM-5-TR / ICD-11 6C70–6C7Z ▸ Kleptomania DSM-5-TR / ICD-11 6C70–6C7Z ▸ Other specified / unspecified disruptive, impulse-control and conduct disorder DSM-5-TR ▸ Substance use disorders (alcohol, cannabis, opioid, stimulant, tobacco, inhalant, sedative, hallucinogen) DSM-5-TR / ICD-11 6C40–6C4Z ▸ Gambling Disorder DSM-5-TR / ICD-11 6C50–6C5Z ▸ Gaming Disorder / Internet Gaming Disorder ICD-11 6C51 | N36: PRESENTATIONS WITH NO DIAGNOSIS ▸ Harmful or sexualised behaviour in children Not a DSM diagnosis ▸ Adolescent substance misuse / dual diagnosis Not a standalone diagnosis ▸ Unstructured time — yard and corridor as the difficulty Added ▸ Supervision ratio and yard layout Added ▸ Group dynamics and peer influence Added ▸ Risk-taking without a diagnosis attached Added | O36: REFER TO ▸ NEPS ▸ CAMHS ▸ Addiction services ▸ Tusla | P36: — | Q36: ▸ Early Years / Pre-School (0–5) Yard observation · staff report · developmentally, most of this is not yet meaningful — describe rather than classify. | R36: ▸ School Age (6–12) Yard observation (event/frequency recording) · sociometric or friendship mapping · SDQ peer subscale · compare classroom vs yard — the difference is the finding. | S36: ▸ Adolescent (13–16) Corridor and break observation where possible · pupil interview · school incident record · substance screening is not NEPS work — refer. | T36: ▸ Young Adult (17–26) Not typically a NEPS referral at this band. | U36: ▸ Special Setting (class or school) Break-time structure in the setting · supported vs unsupported time · staffing at transitions. | AG36: Environmental Factors — Family, School, Community · Family dynamics (including CEC, adopted and CYP with SGOs) · Siblings, extended family, links and relationship to school and education · Family stressors · Financial stress · Housing · Home learning environment · Parental attitude to school/education · Trauma/significant life events · Adverse childhood events · Family views · Bereavements/relational losses · Key adults / members of staff (significant relationships both positive and negative in and out of school) and level of school commitment to child · Travel distance to school · School attendance · Child's views/preferences · School-parent relationship · Peer group dynamics · School learning environment · Access to interventions and support · Curriculum/exam boards · Teacher expectations · Teacher/staff understanding/knowledge · Attainment-based grouping · Influences in school and the local community · Other agency involvement — Police, YOT, CAMHS, Speech and Language Service, Fair Access, SENAT, Virtual School, SGO Advisor, Intensive Planning Team, Prevent, CSE, Early Years, School Nurse, Portage, Early Help, Social and Caring Services Health Services | AH36: Within-Child — Biological Factors · Family history including early development, physical development, medical conditions and diagnoses/difficulties · General health · Medication · Dietary needs · Sensory needs · Addictions e.g. smoking, drink, drugs | AI36: Within-Child — Cognitive Factors ASSESSABLE · Memory · Language · Executive functioning: including emotional and behavioural regulation/development · Attention and concentration · Visual spatial ability · Phonological processing · Processing speed · Non-verbal reasoning · Verbal ability (e.g. word problems, verbal presentation) · Logical reasoning ability · Literacy skills · Attainment OBSERVATION AND CONSULTATION · Signs of developmental trauma impacting on ability to participate in learning · Ability to problem-solve · Flexibility of thought and action · Self-awareness | AJ36: Within-Child — Affective Factors · Experience of developmental trauma · Confidence · Self-esteem · Emotional understanding and expression · Sense of enablement · Sense of self · Sense of belonging · Motivation (intrinsic or extrinsic) · Resiliency · Mood · Anxiety · Aspirations · Perseverance / determination · Sense of humour · Self-control · Social skills · Empathy | AK36: Within-Child — Behavioural Factors · Ability to develop and maintain friendships and relationships · Positive achievements · Care/concern for others, volunteering, helping · Dangerous or risk-taking behaviour · Verbal / physical abuse · Self-harm · Bullying · Truancy
A37: SKILL | B37: 1. Assessment | C37: ▸ Knowing the content ▸ Interview technique ▸ Holding the emotional content | D37: 2. Structured interviewing of parents for developmental history | E37: Macro skill | F37: 2. Structured interviewing of parents for developmental history | G37: Everything about this skill is on this row. Scroll right. | K37: =COUNTIF(Log!$G$3:$G$402,"2. Structured interviewing of parents for developmental history") | L37: =IF(COUNTIF(Log!$G$3:$G$402,"2. Structured interviewing of parents for developmental history")=0,"",SUMPRODUCT(MAX((Log!$G$3:$G$402="2. Structured interviewing of parents for developmental history")*Log!$A$3:$A$402))) | M37: ▸ CORU 2.2 Be able to modify and adapt communication methods and styles, including verbal and non-verbal methods, to suit the individual service user, considering issues of language, age, culture, beliefs and health and/or social care needs ▸ CORU 3.1 Be able to gather all appropriate background information relevant to the service user's health and social care needs ▸ CORU 5.2 Demonstrate a critical understanding of relevant biological sciences, human development, social and behavioural sciences and other related sciences, together with a knowledge of health and wellbeing ▸ CORU 5.12 Know the psychological theories of education, human development, learning and teaching and their application in children, young people and adult learners | N37: ▸ PSI 1.1.1 Have sensible regard for individual clients' moral and cultural values. ▸ PSI 1.1.3 Convey respect for and abide by prevailing community mores, social customs, and cultural expectations in their scientific and professional activities. ▸ PSI 1.3.5 Ensure at least the following are understood: purpose and nature of the activity; mutual responsibilities; likely benefits and risks; alternatives; consequences of non-action; the option to refuse or withdraw at any time without prejudice; the period the consent applies to; and how to rescind consent. ▸ PSI 1.4.1 Seek as full and active participation as possible from others in decisions which affect them. ▸ PSI 2.2.2 Recognise the boundaries of their competence, and do not exceed these. ▸ PSI 2.3.1 Be mindful, when making decisions based on psychological data and techniques, of the limitations of such data and techniques. | O37: The developmental history is the only source of data covering the first five years, and it is the difference between a profile and a snapshot. It is also the point at which the parent decides whether you are someone they will tell the truth to. Rushing it costs you the information and the relationship at once. | P37: ▸ What the history is actually for You are looking for three things. First, timing: when did each domain come online, and were they in step with each other? A child who walked at 11 months and said first words at 30 months has an uneven profile, and unevenness is more informative than delay. Second, trajectory: has the gap widened, narrowed or stayed constant? A constant gap suggests a stable difference; a widening gap suggests the demands are outpacing the skill. Third, discontinuity: was there a point at which something changed, and what else was happening then? ▸ The domains, and the order to take them in Pregnancy and birth — complications, prematurity, birth weight, time in special care. Early motor — head control, sitting, crawling, walking. Speech and language — babbling, first words, two-word combinations, and crucially whether anyone was worried. Social and play — eye contact, joint attention, pretend play, interest in other children. Self-care — feeding, sleep, toileting, dressing. Medical — illnesses, hospitalisations, hearing and vision checks, medication. Education — preschool, transitions, previous schools, supports already tried. Take them in roughly this order because it is chronological and parents can follow it. Do not jump around; a parent who loses the thread gives shorter answers. ▸ Why sleep, feeding and self-care are the ones people skip They feel intrusive and they are not obviously psychological. They are also where the most useful information often sits. Persistent sleep difficulty affects attention, mood and learning, and is treatable. Restricted eating can indicate sensory difference. Delayed self-care with intact motor skills points somewhere different from delayed self-care with motor difficulty. Skipping these three is the commonest gap in trainee histories. ▸ Asking about strengths first, and why it is not politeness Opening with what the child is good at does two things. It gives you data you will need for the recommendations — you cannot build on a strength you never asked about. And it tells the parent that this is an assessment of a whole child, not a catalogue of deficits, which changes what they are willing to tell you for the next hour. ▸ Handling disclosure without losing the interview Parents disclose bereavement, separation, their own mental health, and sometimes safeguarding concerns. The move is: stop the schedule, acknowledge it plainly, ask one follow-up if it is relevant to the child, then signal the return — 'thank you for telling me that. Can I come back to the early years for a moment?' Do not rush past it and do not abandon the interview. If it crosses a child protection threshold the duty is immediate and separate from the assessment. | Q37: ▸ Carr, A. (2016). The handbook of child and adolescent clinical psychology (3rd ed.). Routledge. — the chapter on intake interviewing. ▸ Frederickson, N., & Cline, T. (2015). Special educational needs, inclusion and diversity (3rd ed.). Open University Press. ▸ PSI (2025). Code of professional ethics (5th rev.). Clauses 1.1.3 and 1.3.5 on respect and informed consent. | R37: ✗ Reading questions off a schedule for the first time in the room. ✗ Skipping sleep, feeding and self-care because they feel intrusive. ✗ Accepting 'normal' or 'fine' as an answer without a follow-up. ✗ Taking the history with the child present when the content is sensitive. ✗ Letting the supervisor lead every time — only leading earns a rating of 3 or above. | S37: ▸ GRADE 3 You covered the schedule with the supervisor leading and the content was complete. ▸ GRADE 4 You led it, covered every domain including the uncomfortable ones, and followed up ambiguity. ▸ GRADE 5 You led it, the parent raised something you had not asked about, and you used it. | T37: ▸ BLOCK 1 · Knowing the content [4–5 hours, once · Weeks 1–2 · Study] What a full developmental history covers and why each domain matters — pregnancy, milestones, speech and language, play, sleep, feeding, medical, family. How you build it: Build your own schedule from a published one. Writing it is what makes you remember it. · Prepare the history schedule and read it beforehand you have it when: You are not reading questions for the first time in the room [CORU SoP 3.1] · Take pregnancy, birth and neonatal history you have it when: You asked about complications without alarming [CORU SoP 5.2] · Take early motor, speech and language milestones you have it when: You have dates or approximations, not impressions [CORU SoP 5.12] · Ask about sleep, feeding and self-care you have it when: You asked — the three most commonly skipped [CORU SoP 5.2] · Ask about play and peer relationships you have it when: You asked about friendships, not only language [CORU SoP 5.15] · Ask about medical history and medication you have it when: You asked what effect it has, not just its name [CORU SoP 5.19] ▸ BLOCK 2 · Interview technique [Builds over 4–5 interviews · Weeks 3–6 · Practice] How to ask so that you get an account rather than answers — opening, following up, not leading. How you build it: Practise on a colleague. Then do three with your supervisor present. · Open with the parent's own concern, in their words you have it when: The parent speaks first and you have not led them [CORU SoP 2.3 · PSI Code 1.4.1] · Ask about strengths before difficulties you have it when: Strengths appear in your notes at all [CORU SoP 1.3] · Follow up an ambiguous answer rather than accepting it you have it when: You noticed the ambiguity in the moment [CORU SoP 3.1] ▸ BLOCK 3 · Holding the emotional content [2 hours, then case by case · Weeks 3–6 · Practice] What to do when a parent becomes upset, discloses, or says something you were not expecting. How you build it: Ask your supervisor for three things they say when a parent cries. Have your own version ready. · Ask about family structure and significant events sensitively you have it when: You did not press where the parent hesitated [CORU SoP 1.8 · PSI Code 1.1.3] · Manage emotional disclosure without losing the thread you have it when: You held both the person and the task [CORU SoP 2.2 · PSI Code 1.1.1] · Close with what happens next and when you have it when: The parent leaves knowing the timeline [PSI Code 1.3.5] | U37: No full chapter yet. | V37: ▸ 1.1 Attention, concentration and work skills full entry under 1. Observation in classroom, playground and clinic ▸ 1.2 Language skills full entry under 1. Observation in classroom, playground and clinic ▸ 1.3 Comprehension and general ability full entry under 4. WISC-V administration to proficiency standard ▸ 1.6 Co-ordination — fine motor / handwriting, gross motor / PE skills full entry under 1. Observation in classroom, playground and clinic ▸ 5.4 Concerns about early development FULL ENTRY HERE | W37: Table 2 area 1 · Appendix 5 tagged Assessment · Appendix 7 observation · Table 3 tools and categories | X37: Equal Status Acts 2000–2018 — reasonable accommodation · GDPR — lawful basis, minimisation | Y37: Year 1 — Extends to developmental histories in disability services in Year 2.
A38: AREA | B38: 1. Assessment | D38: 2. Structured interviewing of parents for developmental history | E38: Referral area | F38: 5.4 Concerns about early development | G38: ON THE FORM — Section 5 | K38: =COUNTIF(Log!$E$3:$E$402,"5.4 Concerns about early development") | L38: =IF(COUNTIF(Log!$E$3:$E$402,"5.4 Concerns about early development")=0,"",SUMPRODUCT(MAX((Log!$E$3:$E$402="5.4 Concerns about early development")*Log!$A$3:$A$402))) | M38: No diagnoses. Everything here is a presentation. | N38: PRESENTATIONS WITH NO DIAGNOSIS ▸ Parent-infant mental health / 0–3 attachment work Not a DSM diagnosis ▸ Early Intervention Team caseload (0–6, pre-diagnostic) Not a DSM diagnosis ▸ Delayed developmental milestones Not a DSM diagnosis ▸ AIM level and preschool support already in place Added ▸ Transition from preschool to primary Added | O38: REFER TO ▸ CDNT 0–6 teams ▸ Primary Care ▸ CDNT ▸ Public Health Nurse ▸ Paediatrics ▸ AIM ▸ NEPS ▸ SENO | P38: — | Q38: ▸ Early Years / Pre-School (0–5) This is the band. Developmental history · PHN records · Schedule of Growing Skills · Griffiths III via CDNT · AIM and preschool staff consultation · NEPS involvement here is usually consultation, not assessment. This is your hardest band to cover on placement — plan it deliberately. | R38: ▸ School Age (6–12) Retrospective developmental history informs the current picture. | S38: ▸ Adolescent (13–16) — | T38: ▸ Young Adult (17–26) — | U38: ▸ Special Setting (class or school) Early intervention class or unit · AIM supports. | AG38: Environmental Factors — Family, School, Community · Family dynamics (including CEC, adopted and CYP with SGOs) · Siblings, extended family, links and relationship to school and education · Family stressors · Financial stress · Housing · Home learning environment · Parental attitude to school/education · Trauma/significant life events · Adverse childhood events · Family views · Bereavements/relational losses · Key adults / members of staff (significant relationships both positive and negative in and out of school) and level of school commitment to child · Travel distance to school · School attendance · Child's views/preferences · School-parent relationship · Peer group dynamics · School learning environment · Access to interventions and support · Curriculum/exam boards · Teacher expectations · Teacher/staff understanding/knowledge · Attainment-based grouping · Influences in school and the local community · Other agency involvement — Police, YOT, CAMHS, Speech and Language Service, Fair Access, SENAT, Virtual School, SGO Advisor, Intensive Planning Team, Prevent, CSE, Early Years, School Nurse, Portage, Early Help, Social and Caring Services Health Services | AH38: Within-Child — Biological Factors · Family history including early development, physical development, medical conditions and diagnoses/difficulties · General health · Medication · Dietary needs · Sensory needs · Addictions e.g. smoking, drink, drugs | AI38: Within-Child — Cognitive Factors ASSESSABLE · Memory · Language · Executive functioning: including emotional and behavioural regulation/development · Attention and concentration · Visual spatial ability · Phonological processing · Processing speed · Non-verbal reasoning · Verbal ability (e.g. word problems, verbal presentation) · Logical reasoning ability · Literacy skills · Attainment OBSERVATION AND CONSULTATION · Signs of developmental trauma impacting on ability to participate in learning · Ability to problem-solve · Flexibility of thought and action · Self-awareness | AJ38: Within-Child — Affective Factors · Experience of developmental trauma · Confidence · Self-esteem · Emotional understanding and expression · Sense of enablement · Sense of self · Sense of belonging · Motivation (intrinsic or extrinsic) · Resiliency · Mood · Anxiety · Aspirations · Perseverance / determination · Sense of humour · Self-control · Social skills · Empathy | AK38: Within-Child — Behavioural Factors · Ability to develop and maintain friendships and relationships · Positive achievements · Care/concern for others, volunteering, helping · Dangerous or risk-taking behaviour · Verbal / physical abuse · Self-harm · Bullying · Truancy
A39: SKILL | B39: 1. Assessment | C39: ▸ Knowing the school system ▸ Getting the right information | D39: 3. Structured interviewing of teachers and SET | E39: Macro skill | F39: 3. Structured interviewing of teachers and SET | G39: Everything about this skill is on this row. Scroll right. | K39: =COUNTIF(Log!$G$3:$G$402,"3. Structured interviewing of teachers and SET") | L39: =IF(COUNTIF(Log!$G$3:$G$402,"3. Structured interviewing of teachers and SET")=0,"",SUMPRODUCT(MAX((Log!$G$3:$G$402="3. Structured interviewing of teachers and SET")*Log!$A$3:$A$402))) | M39: ▸ CORU 3.1 Be able to gather all appropriate background information relevant to the service user's health and social care needs ▸ CORU 5.13 Know the structures and systems of school, community and social settings in which educational, health and social care services are provided for children, young people and adult learners ▸ CORU 5.14 Know the impact of structures and systems in which educational services are provided on the development of children, young people and adult learners at individual, group and organisational levels | N39: ▸ PSI 2.2.2 Recognise the boundaries of their competence, and do not exceed these. ▸ PSI 2.3.1 Be mindful, when making decisions based on psychological data and techniques, of the limitations of such data and techniques. | O39: The teacher holds the comparison data you cannot get anywhere else — how this child compares with thirty others doing the same task in the same room. They also hold the intervention history, and without it your recommendations will repeat what has already failed. | P39: ▸ The Continuum of Support, and why you must place the child on it NEPS operates a three-level model. Classroom Support is what the class teacher does within ordinary differentiated teaching, planned and reviewed informally. School Support adds targeted intervention for a smaller group, with a written support plan and a review cycle, usually involving the SET. School Support Plus is individualised, often drawing on outside professionals including you, with a detailed plan and formal review. The level matters because it tells you what has been tried and what the school's next move can realistically be. Recommending School Support for a child already at School Support Plus tells everyone you did not ask. ▸ Allocation versus deployment Since 2017 special education teaching hours are allocated to schools on a profiled basis rather than per diagnosis — so a diagnosis does not generate hours. How the school then deploys those hours is a separate decision made internally, and two schools with identical allocations can deploy very differently. When you ask about support, ask both questions: what does the school have, and how has it chosen to use it. ▸ Getting a referral question that can be answered Referrals arrive as descriptions, not questions — 'concerns about progress in literacy'. Your job is to convert that into something answerable: is the difficulty specific to literacy or part of a broader profile; is the current intervention appropriate and being delivered as intended; what should happen next. Write your version in one sentence and read it back. If the teacher does not recognise it as theirs, you have not yet got the question. ▸ Asking what has been tried, without it sounding like an audit Teachers often expect to be judged. Frame it as information-gathering: 'What have you already tried, and what did you notice when you did?' The second clause matters — it invites observation rather than justification, and it often produces the most useful data in the interview, because a partially effective intervention tells you more than a failed one. | Q39: ▸ Department of Education and Skills (2017). Continuum of Support: Guidelines for teachers. NEPS. ▸ Department of Education (2017). Circular 0013/2017: Special education teaching allocation. — cite the circular number, not 'guidance'. ▸ NCSE (2014). Delivery for students with special educational needs. — background on the allocation model. | R39: ✗ Assuming nothing has been tried. ✗ Not requesting attainment data until after you have met the child. ✗ Taking the referral wording at face value. ✗ Interviewing the person who is available rather than the person who knows the child best. ✗ Not agreeing what feedback the school will get, so expectations diverge. | S39: ▸ GRADE 3 You gathered what you were asked to gather. ▸ GRADE 4 You clarified the question, established the Continuum level, and read the attainment data first. ▸ GRADE 5 You arrived knowing what the school had already tried, and your question was one the teacher recognised as theirs. | T39: ▸ BLOCK 1 · Knowing the school system [5–6 hours for the first school · Weeks 1–2 · Study] How SET allocation works, what the Continuum of Support levels are, and what a school can offer at each. How you build it: Read the Continuum documents. Map one school properly. · Place the child on the Continuum of Support you have it when: You know the stage before you recommend anything [NEPS Continuum of Support] · Ask what has already been tried and what happened you have it when: You did not assume nothing had been tried [CORU SoP 5.13] · Ask about presentation across the timetable you have it when: You know whether it varies by subject or teacher [CORU SoP 5.14] ▸ BLOCK 2 · Getting the right information [Habit, not hours · Weeks 3–6 · Habit] Clarifying a vague referral, finding the right informant, and getting the data you need in advance. How you build it: Write the referral question in one sentence before every meeting and check it with the teacher. · Clarify the referral question with the person who raised it you have it when: You can state it in one sentence they recognise [CORU SoP 3.1] · Request standardised attainment data in advance you have it when: You read it before meeting the child [CORU SoP 3.1] · Ask who knows this child best in the school you have it when: You found the right informant, not the available one [CORU SoP 3.1] · Agree what feedback the school gets and when you have it when: Expectations set at the start [CORU SoP 2.1] | U39: No full chapter yet. | V39: ▸ 1.1 Attention, concentration and work skills full entry under 1. Observation in classroom, playground and clinic ▸ 1.2 Language skills full entry under 1. Observation in classroom, playground and clinic ▸ 1.3 Comprehension and general ability full entry under 4. WISC-V administration to proficiency standard ▸ 2.1 Behaviour in class full entry under 1. Observation in classroom, playground and clinic ▸ 4.2 Relationships with adults full entry under 30. Build rapport with a child during assessment | W39: NEPS Continuum of Support · Table 2 area 1 · Appendix 5 tagged Assessment · Appendix 7 observation · Table 3 tools and categories | X39: Equal Status Acts 2000–2018 — reasonable accommodation · GDPR — lawful basis, minimisation | Y39: Year 1 — Extends to multi-disciplinary informants in Year 2.
A40: SKILL | B40: 1. Assessment | C40: ▸ The theory underneath ▸ Knowing the manual ▸ Administration mechanics ▸ The clinical half | D40: 4. WISC-V administration to proficiency standard | E40: Macro skill | F40: 4. WISC-V administration to proficiency standard | G40: Everything about this skill is on this row. Scroll right. | K40: =COUNTIF(Log!$G$3:$G$402,"4. WISC-V administration to proficiency standard") | L40: =IF(COUNTIF(Log!$G$3:$G$402,"4. WISC-V administration to proficiency standard")=0,"",SUMPRODUCT(MAX((Log!$G$3:$G$402="4. WISC-V administration to proficiency standard")*Log!$A$3:$A$402))) | M40: ▸ CORU 5.6 Demonstrate safe and effective implementation of practical, technical and clinical/professional skills ▸ CORU 5.21 Establish, maintain and conclude a professional relationship with a service user, safely and ethically, recognising and managing professional boundaries ▸ CORU 5.31 Conduct a range of assessment methods safely and ethically, adapting and re-evaluating their application as appropriate | N40: ▸ PSI 1.4.3 Respect the right of individuals to discontinue participation or service at any time, and be responsive to non-verbal indications of a desire to discontinue. ▸ PSI 2.2.2 Recognise the boundaries of their competence, and do not exceed these. ▸ PSI 2.3.1 Be mindful, when making decisions based on psychological data and techniques, of the limitations of such data and techniques. ▸ PSI 3.3.6 Take all reasonable steps to ensure tests and assessment methods are only used by those qualified and trained to do so. ▸ PSI 4.3.1 Respect the right of clients and research participants to receive an appropriate explanation of the nature, purpose and results of investigations, assessments and research findings, in language they can understand. | O40: The WISC-V is the instrument you will be judged on most directly — there is a proficiency examination, and administration errors are visible on the protocol to anyone who reads it. It is also the instrument most likely to be over-interpreted. Learning to administer it is a few weeks of work. Learning what it does and does not tell you takes the full three years. | P40: ▸ What the test is built on The WISC-V is organised around the Cattell–Horn–Carroll (CHC) model, which proposes broad ability domains beneath general ability. The five primary indices map onto CHC constructs: Verbal Comprehension (crystallised ability, Gc) — acquired verbal knowledge and reasoning; Visual Spatial (Gv) — perceiving and manipulating spatial relations; Fluid Reasoning (Gf) — novel problem solving with minimal prior knowledge; Working Memory (Gwm) — holding and manipulating information briefly; Processing Speed (Gs) — speed and accuracy on simple visual tasks. The separation of Visual Spatial from Fluid Reasoning was the major change from WISC-IV, where both sat inside Perceptual Reasoning. It matters because a child can be strong at spatial construction and weak at abstract reasoning, and the older structure hid that. ▸ Start points, reverse rules, discontinue rules Start point: where you begin, determined by the child's age, with a lower start if ability is known or suspected to be low. Reverse rule: if the child fails at or near the start point, you administer earlier items backwards until the criterion is met, establishing a true basal. Discontinue rule: after a specified number of consecutive zero scores you stop, because further items would yield nothing and cost the child confidence. The rules vary by subtest. There is no general rule to learn — the work is per-subtest memorisation. The reason hesitation is what an examiner watches for is that hesitating tells them you are computing the rule rather than knowing it, and a child notices the pause. ▸ Querying, prompting, and where the line is A query is a permitted follow-up when a response is ambiguous or incomplete — usually 'tell me more about that'. The manual specifies which responses may be queried and with what wording. A prompt is a permitted reminder of task demands. Neither may be used to steer the child toward a better answer. Over-querying is the commonest integrity failure and it comes from decency — you can see the child nearly has it. Every unpermitted query inflates the score and invalidates the comparison to the norm sample, because the norm sample was not queried that way. If you realise you have over-queried, note it on the protocol and flag it in the report. ▸ Confidence intervals and why point scores mislead Every obtained score contains measurement error. The confidence interval expresses the range within which the true score probably lies — typically reported at 95%. An FSIQ of 97 with a 95% interval of 92–102 is not meaningfully different from one of 103 with an interval of 98–108, though the point scores look different. Report intervals. Writing 'his IQ is 97' is both technically wrong and practically harmful, because schools act on the number. ▸ When an index is not interpretable If the subtests contributing to an index differ substantially from each other (the manual gives the critical values), the index is an average of unlike things and describes no real ability. In that case you report the subtest-level pattern and say the index is not interpretable. This is a genuine skill and it separates a psychologist from an administrator. ▸ The clinical half Scores are half the data. The other half is how the child approached the task: did they plan before starting or dive in; what happened after failure; did they ask for help; did they check their work; was performance affected by time pressure specifically. Write behavioural observations for every administration, including practice ones, and compare them against the scores afterwards. That comparison is how the clinical eye develops. | Q40: ▸ Wechsler, D. (2016). WISC-V UK administration and scoring manual. Pearson. — chapters on administration and standard procedure. ▸ Wechsler, D. (2016). WISC-V UK technical and interpretive manual. Pearson. — chapters 1 and 2 for the theoretical structure. ▸ Flanagan, D. P., & Alfonso, V. C. (2017). Essentials of WISC-V assessment. Wiley. ▸ PSI (2025). Code of professional ethics. Clause 3.3.6 — tests used only by those trained to do so. | R40: ✗ Over-querying to help a child succeed. ✗ Continuing past a discontinue rule out of kindness. ✗ Paraphrasing instructions under time pressure. ✗ Recording a gist rather than the verbatim response, so the protocol cannot be re-scored. ✗ Reporting point scores without confidence intervals. ✗ Interpreting an index when subtest scatter makes it uninterpretable. ✗ Taking no behavioural observations, so you have scores and nothing else. | S40: ▸ GRADE 3 No rule errors, but you were watching the manual rather than the child. ▸ GRADE 4 Fluent administration, accurate scoring, adaptations annotated as they happened. ▸ GRADE 5 Fluent enough to watch the child; you can say what the profile does not establish. | T40: ▸ BLOCK 1 · The theory underneath [6–8 hours, once · Before placement · Study] The CHC model, what each of the five indices claims to measure, and why they are separated. How you build it: Technical and Interpretive Manual chapters 1–2, plus one CHC overview paper. · Understand what each index measures you have it when: You can explain VCI and FRI to a parent in plain words [CORU SoP 5.1 · 5.15] · Know what the test does not measure you have it when: You can say what a WISC-V cannot tell you [PSI Code 2.3.1] ▸ BLOCK 2 · Knowing the manual [10–15 hours over several weeks · Before placement · Study] Start points by age, reverse rules, discontinue rules, timing, and permitted queries — per subtest, not in general. How you build it: Make a one-page crib per subtest. Test yourself until you never reach for the manual. · Apply start points correctly for age and ability you have it when: You knew the rule without checking mid-session [CORU SoP 5.6] · Apply reverse rules without hesitating you have it when: Hesitation is what the examiner watches for [CORU SoP 5.6] · Apply discontinue rules correctly you have it when: You did not continue past discontinue to be kind [CORU SoP 5.6] · Query and prompt only where the manual permits you have it when: You did not over-query to help the child succeed [CORU SoP 5.31 · PSI Code 3.3.6] ▸ BLOCK 3 · Administration mechanics [15–20 hours · Weeks 1–2 · Practice] Materials handling, seating, stopwatch, verbatim recording, Q and P notation, pacing. How you build it: Practise on adults first, then a child you are not assessing. Six full practice administrations before a real one. · Prepare and check the kit before the child arrives you have it when: Nothing is missing mid-subtest [CORU SoP 5.6] · Set up table and seating correctly you have it when: Child sees the stimulus book, you see the record form [CORU SoP 5.6] · Read instructions verbatim you have it when: You did not paraphrase under time pressure [CORU SoP 5.6] · Time accurately while managing engagement you have it when: Timing did not slip while you managed behaviour [CORU SoP 5.6] · Record responses verbatim including errors you have it when: Another psychologist could re-score from your protocol [CORU SoP 2.8] · Use the record form correctly including Q and P you have it when: The form is complete and legible [CORU SoP 2.10] ▸ BLOCK 4 · The clinical half [Builds with every administration · Weeks 7–12 · Practice] Rapport, reading the child's state, and knowing when to adapt or stop. How you build it: Write behavioural observations for every administration including practice ones. Compare them with the scores. · Establish rapport before beginning you have it when: The child looks at ease before subtest one [CORU SoP 5.21] · Explain what will happen in language the child understands you have it when: The child could repeat it back roughly [PSI Code 4.3.1] · Notice fatigue, anxiety or disengagement you have it when: You noticed before the child told you [CORU SoP 5.31] · Offer a break and record it at the time you have it when: Annotated on the protocol [CORU SoP 5.31 · Equal Status Acts] · Stop if the child indicates they want to you have it when: You stopped rather than negotiated [PSI Code 1.4.3] · Close so the child leaves feeling competent you have it when: How the child walks out [CORU SoP 5.21] | U40: ▸ 0 – 25% — The instrument and the model beneath it What you must understand before you touch the kit. Nobody administers well who does not know what the test claims to measure. ▸ What an IQ score is [3–4 hours · study] A standard score is a statement about rank, not about quantity. An FSIQ of 100 means the child performed at the median of the standardisation sample for their age. It does not mean they have 100 units of anything. The scale is set with a mean of 100 and a standard deviation of 15, so roughly 68% of children score between 85 and 115, and roughly 95% between 70 and 130. Subtest scaled scores use a different metric — mean 10, standard deviation 3. This is why a scaled score of 7 and an index of 85 mean the same thing: both are one standard deviation below the mean. Trainees regularly misread a scaled score of 7 as poor and an index of 85 as borderline, when they are identical statements. Percentile rank is the most honest thing to report to a school, because it is what people think a standard score means. A score of 85 is the 16th percentile: roughly one child in six scores at or below this. Saying that is clearer than any band label. ▸ The CHC model [6–8 hours · study] Cattell–Horn–Carroll theory is the empirical synthesis underlying most modern cognitive batteries. It is hierarchical: a general factor (g) at stratum III, around eight to ten broad abilities at stratum II, and many narrow abilities at stratum I. It emerged from Carroll's 1993 re-analysis of several hundred factor-analytic datasets, merged with Cattell and Horn's fluid–crystallised distinction. The five WISC-V primary indices map onto CHC broad abilities: Verbal Comprehension to Gc (crystallised knowledge), Visual Spatial to Gv (visual processing), Fluid Reasoning to Gf (fluid reasoning), Working Memory to Gwm (short-term working memory), Processing Speed to Gs. The WISC-V split Visual Spatial from Fluid Reasoning, which WISC-IV had merged into Perceptual Reasoning. The change matters clinically: a child can build a block design accurately and still be unable to reason about a novel matrix, and the older structure averaged those into one number that described neither. ▸ What each index is actually made of [4–5 hours · study] Verbal Comprehension: Similarities (abstract verbal reasoning about category membership) and Vocabulary (word knowledge and expression). Both are heavily influenced by language exposure and schooling, which is why VCI is the index most affected by EAL status and socioeconomic background. Visual Spatial: Block Design (construction from a model, timed) and Visual Puzzles (mental assembly, no motor component). The pairing is deliberate — a discrepancy between them points at motor or speed factors rather than spatial reasoning. Fluid Reasoning: Matrix Reasoning (pattern completion) and Figure Weights (quantitative analogical reasoning). Figure Weights is the more demanding and loads more heavily on g. Working Memory: Digit Span (auditory) and Picture Span (visual). Digit Span itself splits into forward (short-term storage), backward (manipulation) and sequencing (manipulation with reordering) — and these three can dissociate. Processing Speed: Coding (paired-associate copying under time pressure) and Symbol Search (visual discrimination under time pressure). Both are sensitive to motor speed, attention, anxiety and motivation, which is why a low PSI is the least specific finding on the test. ▸ Test construction concepts you need [5–6 hours · study] Standardisation sample: the UK WISC-V was normed on a representative sample stratified by age, sex, parental education and region. Every score you report is a comparison to that sample. This is why departures from standard procedure matter — the sample was not tested that way. Reliability: the consistency of measurement. Internal consistency for the composites is high (generally above .90 for FSIQ); subtest reliabilities are lower (many in the .80s), which is one statistical reason subtest-level interpretation is weaker than index-level. Standard error of measurement: derived from reliability, it quantifies how much an obtained score would be expected to vary on retesting. It generates the confidence interval, and it is the reason a point score is a false precision. Validity: whether the test measures what it claims. Construct validity for the WISC-V rests on factor-analytic evidence, and the adequacy of that evidence is contested — see stage four. ▸ 25 – 50% — Administration to standard The mechanical competence the proficiency examination tests. Finishable in weeks, and the floor rather than the ceiling. ▸ The rule architecture [10–15 hours · study] Three rule types govern every subtest and they exist for different reasons. Start points, determined by age, save time by not administering items the child will almost certainly pass. Reverse rules exist to establish a basal — a point below which you can safely assume all items would be passed — when a child fails at or near their age-appropriate start. Discontinue rules establish a ceiling, stopping after a specified run of zero scores because further items yield no information and cost the child confidence. The rules differ by subtest and there is no master rule to learn. Build a one-page crib per subtest and test yourself until you never reach for the manual. The reason hesitation is what examiners watch for is that it signals you are computing rather than knowing, and the child hears the pause as a judgement on their answer. A reversal error is the most consequential administration mistake because it changes the basal, which changes the raw score, which changes the scaled score, which changes the index. It is not a technicality. ▸ Querying and prompting [3–4 hours · study, then practice] A query is a permitted follow-up when a response is ambiguous, incomplete, or marked in the manual as queryable. The wording is specified — generally a neutral 'tell me more about that'. A prompt is a permitted reminder of the task demand, also specified. Over-querying is the commonest integrity failure among trainees and it comes from decency: you can see the child nearly has it. Each unpermitted query inflates the score relative to a norm sample that was not queried that way, so the comparison no longer holds. Under-querying is a real error too and less discussed. A response that the manual marks as queryable and that you do not query is scored on incomplete information, usually to the child's disadvantage. If you realise you have queried where you should not, note it on the protocol at the time and flag it in the report. The error is recoverable; the concealment is not. ▸ Recording and the protocol as evidence [habit] Record verbatim, including errors, self-corrections and the order in which parts of an answer were given. The test is whether another psychologist could re-score your protocol and arrive at the same scaled scores. If they could not, you have not recorded, you have summarised. Use the Q and P notation consistently so a reader can see where you queried and prompted. An unannotated protocol looks either perfect or careless, and reviewers assume the latter. The protocol is a clinical record. It is discoverable, it may be read by a supervisor, an examiner, or in a dispute. Write it as though it will be. ▸ The clinical layer during administration [builds with every administration] Scores are half the data. The other half is approach: did the child plan before starting or dive in; what happened after a failure; did they ask for help or work in silence; did they check their answers; was performance worse specifically under time pressure; did they fatigue across the session. These observations are what make a report about a child rather than about a profile. They also generate the hypotheses the formulation tests. Write three sentences of behavioural observation immediately after every administration, including practice ones, and compare them against the scores afterwards. That comparison is how a clinical eye develops — there is no shortcut and no reading that substitutes for it. ▸ 50 – 75% — Scoring and interpretation Where most trainees stop, and where the difference between a 3 and a 5 sits. ▸ From raw to reportable [6–8 hours · study] Raw scores convert to scaled scores using the age-band table for the child's exact age in years and months. Using the wrong age band is a silent error that produces a plausible but wrong profile — check the date of birth calculation twice. Scaled scores sum to composites, which convert to index scores. Hand-score three protocols before using software, and have all three checked. Software prevents arithmetic errors; it does not prevent transcription errors, and a single transposed digit changes a composite. Report the 95% confidence interval with every composite. An FSIQ of 97 (92–102) and one of 103 (98–108) overlap substantially and are not meaningfully different, although the point scores invite a school to treat them as such. ▸ Normative and ipsative comparison [ongoing] There are two questions you can ask of any score. The normative question: how does this child compare to other children of the same age? The ipsative question: how does this ability compare to this child's own average? They give different answers and address different concerns. A child with a uniformly low profile has no ipsative weaknesses but substantial normative ones. A child with a high average profile and one index at 95 has an ipsative weakness at a normatively average level. Confusing the two produces reports that recommend intervention for abilities that are perfectly adequate, or that miss global difficulty because everything is even. Base rates matter. The manual gives the frequency of any given discrepancy in the standardisation sample. A difference that is statistically significant may still occur in 30% of children, which makes it unremarkable. Always check the base rate before calling something a relative weakness. ▸ When an index cannot be interpreted [ongoing] If the two subtests composing an index differ substantially from each other — the manual provides critical values — the index is an average of unlike things and describes no coherent ability. In that case report the subtest-level pattern and state that the index is not interpretable. The same logic applies upward. A FSIQ derived from widely scattered indices is arithmetically correct and clinically meaningless. Where scatter is substantial, the General Ability Index (which excludes working memory and processing speed) is sometimes more representative — but say why you have used it, because substituting GAI for FSIQ without explanation reads as choosing the flattering number. ▸ The ancillary and complementary indices [4–5 hours · study] Beyond the five primary indices the WISC-V offers ancillary composites: Quantitative Reasoning, Auditory Working Memory, Non-verbal, General Ability, and Cognitive Proficiency. Each answers a specific question. The Non-verbal Index is useful where language is a confound — EAL, expressive language difficulty, selective mutism. Cognitive Proficiency combines working memory and processing speed, and a large GAI–CPI split is a recognised pattern in specific learning difficulty. Complementary subtests cover naming speed, symbol translation and storage and retrieval. These were added with dyslexia assessment in view, and they are the part of the battery trainees most often skip. Whether they add incremental value beyond existing measures is not fully settled — use them deliberately, not reflexively. ▸ Writing interpretation that survives scrutiny [ongoing] Interpretation is an argument, not a description. State the pattern, state the evidence for it, state what does not fit, and state what would change your mind. A report that contains no 'however' has almost certainly smoothed something away. Anchor every claim to a specific finding. 'Working memory difficulties are likely to affect multi-step instructions in class' is defensible if AWMI is low; 'he struggles to concentrate' is not, because the WISC-V does not measure concentration. Say explicitly what the assessment does not establish. The WISC-V does not diagnose ADHD, autism, or dyslexia. It contributes to a formulation. Writing this plainly is the difference between a psychologist and a scorer. ▸ 75 – 100% — What experts know that the manual does not say The contested ground. Knowing this is what separates someone who administers the test from someone who can defend its use. ▸ The factor-structure controversy [6–8 hours · reading] The five-factor structure the WISC-V reports is not universally accepted. Independent re-analyses using bifactor modelling — principally by Canivez, Watkins and colleagues — have found that the general factor accounts for the large majority of common variance, and that the group factors beyond g account for relatively little once g is extracted. The practical implication is contested but serious: if the group factors carry little reliable unique variance, index-level interpretation rests on weaker ground than the manual implies, and the FSIQ may be the only score with strong support. Pearson's position, and that of other researchers, is that the confirmatory models in the technical manual support the five-factor structure and that the bifactor findings do not invalidate index interpretation. This disagreement is live and you should know it exists. The defensible practice is to treat index scores as hypotheses to be corroborated by other evidence, rather than as findings in themselves — which is what a strong report does anyway. ▸ Profile analysis and its evidence base [5–6 hours · reading] Subtest profile analysis — inferring specific processing strengths and weaknesses from the shape of the subtest profile — has been standard clinical practice for decades and has substantially poorer empirical support than its popularity suggests. Watkins and others have shown that subtest profiles have limited reliability, limited diagnostic utility and limited value in predicting treatment response. The core statistical problem is that subtest scores have lower reliability than composites, and difference scores between two unreliable measures are less reliable than either. A dramatic-looking peak or trough may be noise. What this means in practice is not that you ignore the profile, but that you treat it as hypothesis-generating rather than conclusion-supporting. A pattern is worth pursuing when corroborated by attainment data, observation and history. It is not worth reporting on its own. ▸ The Flynn effect and norm obsolescence [3–4 hours · reading] Measured IQ rose across the twentieth century at roughly three points per decade in developed countries — the Flynn effect. Because tests are renormed periodically, a child tested on an older instrument will tend to obtain a higher score than on a newer one, simply because they are compared with an older, lower-performing sample. The practical consequence is that scores from different instruments or different editions are not interchangeable, and a child near a threshold can move across it by changing test. Where eligibility depends on a cut-off this is a real justice issue, and it is a reason to state the instrument and edition in the report. Evidence in recent decades is mixed, with some populations showing stagnation or reversal. Do not assume the classic gradient still holds; check the current literature when it matters. ▸ Bias, fairness and what the test cannot see [5–6 hours · reading] Group mean differences on cognitive tests are well documented and their interpretation is deeply contested. What is not seriously contested is that measured performance is influenced by language exposure, schooling quality, socioeconomic circumstance, familiarity with testing, and stereotype threat — none of which are properties of the child's cognition. For EAL children the Verbal Comprehension Index is the most affected and the Non-verbal Index is often the fairer comparison, though no index is culture-free. State the child's language history in the report and interpret verbal scores in that light. The appropriate professional stance is not to avoid the instrument but to be precise about what a score licenses you to say. A low VCI in a child who has been in English-medium education for eighteen months is a statement about language exposure, not about verbal reasoning capacity. ▸ Knowing when not to use it [ongoing] The expert question is not how to administer the WISC-V but whether to. It is the wrong instrument when the referral question is about progress over time (use curriculum-based measurement), about function in context (use observation and consultation), about a specific skill (use a targeted attainment measure), or when a recent administration exists and practice effects would contaminate a retest. Practice effects on the WISC-V are meaningful over short intervals, particularly on Processing Speed and Visual Spatial subtests. A retest within twelve months should be justified explicitly and interpreted with caution. Cross-battery assessment approaches argue for selecting subtests across instruments to cover CHC domains the referral question implicates, rather than administering one full battery by default. This is a defensible expert practice and it requires knowing the CHC map well enough to build a battery deliberately. Choosing not to assess, and saying why, is a higher-level demonstration of the competency than any administration. CORU 3.2 requires you to justify selection; that includes justifying non-selection. | V40: ▸ 1.1 Attention, concentration and work skills full entry under 1. Observation in classroom, playground and clinic ▸ 1.2 Language skills full entry under 1. Observation in classroom, playground and clinic ▸ 1.3 Comprehension and general ability FULL ENTRY HERE | W40: Table 2 area 1 · Appendix 5 tagged Assessment · Appendix 7 observation · Table 3 tools and categories | X40: Equal Status Acts · Equal Status Acts 2000–2018 — reasonable accommodation · GDPR — lawful basis, minimisation | Y40: Year 1 — Proficiency exam in Y1 T2; selection rather than administration becomes the skill from Year 2.
A41: AREA | B41: 1. Assessment | D41: 4. WISC-V administration to proficiency standard | E41: Referral area | F41: 1.3 Comprehension and general ability | G41: ON THE FORM — Section 5 | K41: =COUNTIF(Log!$E$3:$E$402,"1.3 Comprehension and general ability") | L41: =IF(COUNTIF(Log!$E$3:$E$402,"1.3 Comprehension and general ability")=0,"",SUMPRODUCT(MAX((Log!$E$3:$E$402="1.3 Comprehension and general ability")*Log!$A$3:$A$402))) | M41: DIAGNOSES ▸ Intellectual Disability — mild DSM-5-TR / ICD-11 6A00 ▸ Intellectual Disability — moderate DSM-5-TR / ICD-11 6A00 ▸ Intellectual Disability — severe DSM-5-TR / ICD-11 6A00 ▸ Intellectual Disability — profound DSM-5-TR / ICD-11 6A00 ▸ Unspecified Intellectual Disability DSM-5-TR / ICD-11 6A00 ▸ Global Developmental Delay DSM-5-TR / ICD-11 6A00 ▸ Borderline Intellectual Functioning (FSIQ approx. 70–79) DSM-5-TR V-code ▸ Other specified / unspecified neurodevelopmental disorder DSM-5-TR / ICD-11 6A0Z | N41: PRESENTATIONS WITH NO DIAGNOSIS ▸ Cognitive profile differences (verbal, fluid, working memory, processing speed) Not a DSM diagnosis ▸ Underachievement not meeting SLD criteria Not a DSM diagnosis ▸ Giftedness / exceptional ability Not a DSM diagnosis ▸ Twice exceptional (high ability plus SLD, ADHD or ASD) Not a DSM diagnosis ▸ Understanding and responding to adult direction Added — Form 2 wording ▸ Curriculum access at the current level Added ▸ Interrupted or missed schooling Added | O41: REFER TO ▸ CDNT ▸ NEPS — below GLD threshold, significant school impact ▸ NEPS ▸ Educational Welfare | P41: — | Q41: ▸ Early Years / Pre-School (0–5) WPPSI-IV (2:6–7:7) · Vineland-3 or ABAS-3 adaptive · developmental history · caution: large index gaps are less stable at this age than at school age. | R41: ▸ School Age (6–12) WISC-V (6:0–16:11) · WIAT-III for attainment comparison · ABAS-3 or Vineland-3 where ID is in question · GAI instead of FSIQ where index scatter exceeds 23 points. | S41: ▸ Adolescent (13–16) WISC-V to 16:11, then WAIS-IV · adaptive measure · attainment · RACE and subject-choice implications · post-school transition planning starts here. | T41: ▸ Young Adult (17–26) WAIS-IV · ABAS-3 adult form · functional and vocational focus rather than curriculum · eligibility evidence for adult services. | U41: ▸ Special Setting (class or school) Non-verbal options (Leiter-3) where the standard battery is not accessible · adaptive measure is usually more informative than IQ · curriculum is likely L1/L2 LCA — assess against that. | AG41: Environmental Factors — Family, School, Community · Family dynamics (including CEC, adopted and CYP with SGOs) · Siblings, extended family, links and relationship to school and education · Family stressors · Financial stress · Housing · Home learning environment · Parental attitude to school/education · Trauma/significant life events · Adverse childhood events · Family views · Bereavements/relational losses · Key adults / members of staff (significant relationships both positive and negative in and out of school) and level of school commitment to child · Travel distance to school · School attendance · Child's views/preferences · School-parent relationship · Peer group dynamics · School learning environment · Access to interventions and support · Curriculum/exam boards · Teacher expectations · Teacher/staff understanding/knowledge · Attainment-based grouping · Influences in school and the local community · Other agency involvement — Police, YOT, CAMHS, Speech and Language Service, Fair Access, SENAT, Virtual School, SGO Advisor, Intensive Planning Team, Prevent, CSE, Early Years, School Nurse, Portage, Early Help, Social and Caring Services Health Services | AH41: Within-Child — Biological Factors · Family history including early development, physical development, medical conditions and diagnoses/difficulties · General health · Medication · Dietary needs · Sensory needs · Addictions e.g. smoking, drink, drugs | AI41: Within-Child — Cognitive Factors ASSESSABLE · Memory · Language · Executive functioning: including emotional and behavioural regulation/development · Attention and concentration · Visual spatial ability · Phonological processing · Processing speed · Non-verbal reasoning · Verbal ability (e.g. word problems, verbal presentation) · Logical reasoning ability · Literacy skills · Attainment OBSERVATION AND CONSULTATION · Signs of developmental trauma impacting on ability to participate in learning · Ability to problem-solve · Flexibility of thought and action · Self-awareness | AJ41: Within-Child — Affective Factors · Experience of developmental trauma · Confidence · Self-esteem · Emotional understanding and expression · Sense of enablement · Sense of self · Sense of belonging · Motivation (intrinsic or extrinsic) · Resiliency · Mood · Anxiety · Aspirations · Perseverance / determination · Sense of humour · Self-control · Social skills · Empathy | AK41: Within-Child — Behavioural Factors · Ability to develop and maintain friendships and relationships · Positive achievements · Care/concern for others, volunteering, helping · Dangerous or risk-taking behaviour · Verbal / physical abuse · Self-harm · Bullying · Truancy
A42: SKILL | B42: 1. Assessment | C42: ▸ Selection ▸ Administration ▸ Scoring ▸ Interpretation | D42: 5. WIAT administration, scoring and interpretation | E42: Macro skill | F42: 5. WIAT administration, scoring and interpretation | G42: Everything about this skill is on this row. Scroll right. | K42: =COUNTIF(Log!$G$3:$G$402,"5. WIAT administration, scoring and interpretation") | L42: =IF(COUNTIF(Log!$G$3:$G$402,"5. WIAT administration, scoring and interpretation")=0,"",SUMPRODUCT(MAX((Log!$G$3:$G$402="5. WIAT administration, scoring and interpretation")*Log!$A$3:$A$402))) | M42: ▸ CORU 3.2 Be able to justify the selection of and implement appropriate assessment techniques and be able to undertake and record a thorough, sensitive and detailed assessment ▸ CORU 3.3 Be able to determine the appropriate tests/assessments required and undertake/arrange these tests ▸ CORU 5.6 Demonstrate safe and effective implementation of practical, technical and clinical/professional skills ▸ CORU 5.32 Interpret, synthesise and critically evaluate assessment data, within relevant conceptual frameworks, to inform case formulation and psychological intervention planning | N42: ▸ PSI 2.2.2 Recognise the boundaries of their competence, and do not exceed these. ▸ PSI 2.3.1 Be mindful, when making decisions based on psychological data and techniques, of the limitations of such data and techniques. ▸ PSI 4.2.2 Take due care to avoid misrepresentation, exaggeration, distortion or errors in reporting assessment results, research findings or service effectiveness, and act quickly to correct any such error. | O42: Attainment testing answers a different question from cognitive testing: not what can this child do in principle, but what have they learned. The interesting data is in the relationship between the two, and that relationship is the most misused finding in educational psychology. | P42: ▸ Choosing subtests, and why you must justify omission A full battery is rarely warranted. Select for the referral question: word reading and reading comprehension for a literacy referral; numerical operations and maths problem solving for numeracy; spelling and written expression where writing is the concern. Write your rationale before you assess. If you cannot justify the battery beforehand, the battery is wrong — and a report reviewer will notice that you tested everything rather than deciding anything. ▸ The ability–attainment discrepancy, and its limits A gap between measured ability and measured attainment was once treated as diagnostic of a specific learning difficulty. It no longer is, for three reasons. Regression to the mean makes some discrepancy statistically expected. The discrepancy model identifies children late, because a young child has not yet had time to fall far enough behind. And it systematically misses children whose ability score is itself depressed by the difficulty — a child with a reading difficulty scores lower on verbal subtests because of reduced print exposure. What a discrepancy does tell you is that attainment is out of step with other functioning, which warrants explanation. It does not by itself name the explanation. Say that in the report. ▸ Basal, ceiling and the mechanics of scoring Attainment subtests use basal and ceiling rules rather than the reverse-rule structure of cognitive subtests. Establish the basal by working backwards until the required consecutive correct responses are obtained; stop at the ceiling after the required consecutive errors. Score the same day, while you can still read your own handwriting and recall ambiguous responses. Check every raw-to-scaled conversion: a single transcription error changes a composite, and composites are what people act on. ▸ Curriculum-based measurement as an alternative Standardised attainment tests tell you where a child sits against a norm group. They do not tell you whether an intervention is working, because they are insensitive to short-term change and cannot be repeated frequently. Curriculum-based measures — brief, repeatable probes drawn from the curriculum — are better for monitoring. Use the standardised test to establish the profile; use CBM to track progress. Knowing when not to reach for the standardised instrument is part of the competency. | Q42: ▸ Wechsler, D. (2017). WIAT-III UK administration and scoring manual. Pearson. ▸ Fletcher, J. M., Lyon, G. R., Fuchs, L. S., & Barnes, M. A. (2019). Learning disabilities: From identification to intervention (2nd ed.). Guilford. — the chapter on identification models. ▸ CORU (2023). Standards of proficiency. Standards 3.2, 3.3, 5.32. | R42: ✗ Administering the full battery because it is there. ✗ Treating a discrepancy as a diagnosis. ✗ Reporting point scores without intervals. ✗ Leaving scoring to accumulate until the end of the week. ✗ Not noticing a score that contradicts everything else and reporting it anyway. | S42: ▸ GRADE 3 Scores are correct and reported as points. ▸ GRADE 4 Battery justified in writing, intervals applied, discrepancy interpreted cautiously. ▸ GRADE 5 You reported ranges and said what the gap does not prove. | T42: ▸ BLOCK 1 · Selection [2 hours, then 10 minutes per case · Weeks 3–6 · Habit] Which subtests answer which question, and what omitting one costs you. How you build it: Write your rationale before assessing, for five cases. · Select subtests matched to the referral question you have it when: You can justify omitting what you omitted [CORU SoP 3.2 · 3.3] ▸ BLOCK 2 · Administration [6–8 hours · Weeks 3–6 · Practice] Standard administration of reading, spelling and numerical subtests. How you build it: Three supervised practice administrations. · Administer to standard you have it when: Errors would not change the composite [CORU SoP 5.6] ▸ BLOCK 3 · Scoring [6–8 hours, then 45 min per protocol · Weeks 3–6 · Study] Raw to scaled conversion, composites, confidence intervals. How you build it: Score three protocols by hand before using software. Have all three checked. · Score the protocol the same day you have it when: Scoring is not left to accumulate [CORU SoP 2.8] · Check every raw-to-scaled conversion you have it when: One transcription error changes an index [CORU SoP 5.6] · Apply confidence intervals rather than point scores you have it when: The report does not imply false precision [PSI Code 4.2.2] ▸ BLOCK 4 · Interpretation [Ongoing — Year 3 competence · Ongoing all year · Practice] What an attainment–ability discrepancy does and does not establish. How you build it: Read three reports by experienced EPs. Bring one profile to supervision. · Compare attainment against cognitive profile appropriately you have it when: You know what the discrepancy does not mean [CORU SoP 5.32 · PSI Code 2.3.1] · Notice a score you do not believe and check it you have it when: You re-scored rather than reported it [CORU SoP 3.4] | U42: No full chapter yet. | V42: ▸ 1.3 Comprehension and general ability full entry under 4. WISC-V administration to proficiency standard ▸ 1.4 Literacy — reading (fluency / comprehension), writing and spelling FULL ENTRY HERE ▸ 1.5 Maths skills — concepts and computation FULL ENTRY HERE | W42: Table 2 area 1 · Appendix 5 tagged Assessment · Appendix 7 observation · Table 3 tools and categories | X42: Equal Status Acts 2000–2018 — reasonable accommodation · GDPR — lawful basis, minimisation | Y42: Year 1 — Joined by other attainment batteries in Year 2.
A43: AREA | B43: 1. Assessment | D43: 5. WIAT administration, scoring and interpretation | E43: Referral area | F43: 1.4 Literacy — reading (fluency / comprehension), writing and spelling | G43: ON THE FORM — Section 5 | K43: =COUNTIF(Log!$E$3:$E$402,"1.4 Literacy — reading (fluency / comprehension), writing and spelling") | L43: =IF(COUNTIF(Log!$E$3:$E$402,"1.4 Literacy — reading (fluency / comprehension), writing and spelling")=0,"",SUMPRODUCT(MAX((Log!$E$3:$E$402="1.4 Literacy — reading (fluency / comprehension), writing and spelling")*Log!$A$3:$A$402))) | M43: DIAGNOSES ▸ Specific Learning Disorder with impairment in reading (dyslexia) DSM-5-TR ▸ Specific Learning Disorder with impairment in written expression (dysgraphia) DSM-5-TR | N43: PRESENTATIONS WITH NO DIAGNOSIS ▸ Auditory processing concerns Not a DSM diagnosis ▸ Literacy difficulty not meeting SLD criteria Added ▸ Reading stamina and avoidance of reading aloud Added ▸ Handwriting speed and legibility under time pressure Added ▸ Spelling as a barrier to written output Added ▸ Assistive technology not yet trialled Added ▸ Instruction history — what has actually been taught Added — rule out before concluding disorder | O43: REFER TO ▸ NEPS ▸ Audiology ▸ SLT ▸ OT if motor ▸ SENO | P43: — | Q43: ▸ Early Years / Pre-School (0–5) Pre-literacy only: phonological awareness, rhyme, alliteration, letter-sound knowledge · print awareness · do not assess for dyslexia at this age — describe the precursors. | R43: ▸ School Age (6–12) WIAT-III (Word Reading, Reading Comprehension, Spelling, Written Expression) · Neale Analysis · YARC · school Micra-T/Drumcondra · phonological processing · compare against WISC-V and against instruction received. | S43: ▸ Adolescent (13–16) WIAT-III · DASH (handwriting speed) · exam-script analysis · RACE evidence — spelling and grammar waiver, reader, scribe, word processor · subject-teacher survey. | T43: ▸ Young Adult (17–26) WIAT-III or WRAT-5 adult norms · DASH-17+ · DSA evidence for third level · workplace literacy demands. | U43: ▸ Special Setting (class or school) Assess against the setting curriculum · functional literacy (signs, forms, money) may matter more than standardised scores. | AG43: Environmental Factors — Family, School, Community · Family dynamics (including CEC, adopted and CYP with SGOs) · Siblings, extended family, links and relationship to school and education · Family stressors · Financial stress · Housing · Home learning environment · Parental attitude to school/education · Trauma/significant life events · Adverse childhood events · Family views · Bereavements/relational losses · Key adults / members of staff (significant relationships both positive and negative in and out of school) and level of school commitment to child · Travel distance to school · School attendance · Child's views/preferences · School-parent relationship · Peer group dynamics · School learning environment · Access to interventions and support · Curriculum/exam boards · Teacher expectations · Teacher/staff understanding/knowledge · Attainment-based grouping · Influences in school and the local community · Other agency involvement — Police, YOT, CAMHS, Speech and Language Service, Fair Access, SENAT, Virtual School, SGO Advisor, Intensive Planning Team, Prevent, CSE, Early Years, School Nurse, Portage, Early Help, Social and Caring Services Health Services | AH43: Within-Child — Biological Factors · Family history including early development, physical development, medical conditions and diagnoses/difficulties · General health · Medication · Dietary needs · Sensory needs · Addictions e.g. smoking, drink, drugs | AI43: Within-Child — Cognitive Factors ASSESSABLE · Memory · Language · Executive functioning: including emotional and behavioural regulation/development · Attention and concentration · Visual spatial ability · Phonological processing · Processing speed · Non-verbal reasoning · Verbal ability (e.g. word problems, verbal presentation) · Logical reasoning ability · Literacy skills · Attainment OBSERVATION AND CONSULTATION · Signs of developmental trauma impacting on ability to participate in learning · Ability to problem-solve · Flexibility of thought and action · Self-awareness | AJ43: Within-Child — Affective Factors · Experience of developmental trauma · Confidence · Self-esteem · Emotional understanding and expression · Sense of enablement · Sense of self · Sense of belonging · Motivation (intrinsic or extrinsic) · Resiliency · Mood · Anxiety · Aspirations · Perseverance / determination · Sense of humour · Self-control · Social skills · Empathy | AK43: Within-Child — Behavioural Factors · Ability to develop and maintain friendships and relationships · Positive achievements · Care/concern for others, volunteering, helping · Dangerous or risk-taking behaviour · Verbal / physical abuse · Self-harm · Bullying · Truancy
A44: AREA | B44: 1. Assessment | D44: 5. WIAT administration, scoring and interpretation | E44: Referral area | F44: 1.5 Maths skills — concepts and computation | G44: ON THE FORM — Section 5 | K44: =COUNTIF(Log!$E$3:$E$402,"1.5 Maths skills — concepts and computation") | L44: =IF(COUNTIF(Log!$E$3:$E$402,"1.5 Maths skills — concepts and computation")=0,"",SUMPRODUCT(MAX((Log!$E$3:$E$402="1.5 Maths skills — concepts and computation")*Log!$A$3:$A$402))) | M44: DIAGNOSES ▸ Specific Learning Disorder with impairment in mathematics (dyscalculia) DSM-5-TR | N44: PRESENTATIONS WITH NO DIAGNOSIS ▸ Numeracy difficulty not meeting SLD criteria Added ▸ Maths anxiety Added ▸ Number sense and estimation Added ▸ Recall of number facts vs procedural method Added ▸ Word problems — reading as the barrier, not the maths Added ▸ Working memory load in multi-step calculation Added | O44: REFER TO ▸ NEPS | P44: — | Q44: ▸ Early Years / Pre-School (0–5) Early number concepts: counting, one-to-one correspondence, subitising, comparison · observation during play · no standardised maths measure. | R44: ▸ School Age (6–12) WIAT-III Numerical Operations and Maths Problem Solving · Sigma-T · error analysis on actual work · separate the reading load from the calculation load. | S44: ▸ Adolescent (13–16) WIAT-III maths subtests · Junior Certificate results · subject-teacher survey · calculator and formula-sheet access · RACE. | T44: ▸ Young Adult (17–26) WIAT-III/WRAT-5 adult norms · functional numeracy (budgeting, time, measurement) · course-specific demands. | U44: ▸ Special Setting (class or school) Functional numeracy against the setting curriculum · practical application over standardised score. | AG44: Environmental Factors — Family, School, Community · Family dynamics (including CEC, adopted and CYP with SGOs) · Siblings, extended family, links and relationship to school and education · Family stressors · Financial stress · Housing · Home learning environment · Parental attitude to school/education · Trauma/significant life events · Adverse childhood events · Family views · Bereavements/relational losses · Key adults / members of staff (significant relationships both positive and negative in and out of school) and level of school commitment to child · Travel distance to school · School attendance · Child's views/preferences · School-parent relationship · Peer group dynamics · School learning environment · Access to interventions and support · Curriculum/exam boards · Teacher expectations · Teacher/staff understanding/knowledge · Attainment-based grouping · Influences in school and the local community · Other agency involvement — Police, YOT, CAMHS, Speech and Language Service, Fair Access, SENAT, Virtual School, SGO Advisor, Intensive Planning Team, Prevent, CSE, Early Years, School Nurse, Portage, Early Help, Social and Caring Services Health Services | AH44: Within-Child — Biological Factors · Family history including early development, physical development, medical conditions and diagnoses/difficulties · General health · Medication · Dietary needs · Sensory needs · Addictions e.g. smoking, drink, drugs | AI44: Within-Child — Cognitive Factors ASSESSABLE · Memory · Language · Executive functioning: including emotional and behavioural regulation/development · Attention and concentration · Visual spatial ability · Phonological processing · Processing speed · Non-verbal reasoning · Verbal ability (e.g. word problems, verbal presentation) · Logical reasoning ability · Literacy skills · Attainment OBSERVATION AND CONSULTATION · Signs of developmental trauma impacting on ability to participate in learning · Ability to problem-solve · Flexibility of thought and action · Self-awareness | AJ44: Within-Child — Affective Factors · Experience of developmental trauma · Confidence · Self-esteem · Emotional understanding and expression · Sense of enablement · Sense of self · Sense of belonging · Motivation (intrinsic or extrinsic) · Resiliency · Mood · Anxiety · Aspirations · Perseverance / determination · Sense of humour · Self-control · Social skills · Empathy | AK44: Within-Child — Behavioural Factors · Ability to develop and maintain friendships and relationships · Positive achievements · Care/concern for others, volunteering, helping · Dangerous or risk-taking behaviour · Verbal / physical abuse · Self-harm · Bullying · Truancy
A45: SKILL | B45: 1. Assessment | C45: ▸ Seeing the pattern ▸ Writing the synthesis | D45: 6. Synthesise findings from multiple sources into one profile | E45: Macro skill | F45: 6. Synthesise findings from multiple sources into one profile | G45: Everything about this skill is on this row. Scroll right. | K45: =COUNTIF(Log!$G$3:$G$402,"6. Synthesise findings from multiple sources into one profile") | L45: =IF(COUNTIF(Log!$G$3:$G$402,"6. Synthesise findings from multiple sources into one profile")=0,"",SUMPRODUCT(MAX((Log!$G$3:$G$402="6. Synthesise findings from multiple sources into one profile")*Log!$A$3:$A$402))) | M45: ▸ CORU 3.4 Be able to analyse and critically evaluate the information collected in the assessment process ▸ CORU 5.27 Be able to produce clear, concise, accessible and accurate reports — devised in collaboration with service users, as appropriate — that are suitable for the intended audience and context of their use, in order to communicate and justify professional opinions made ▸ CORU 5.32 Interpret, synthesise and critically evaluate assessment data, within relevant conceptual frameworks, to inform case formulation and psychological intervention planning | N45: ▸ PSI 2.3.1 Be mindful, when making decisions based on psychological data and techniques, of the limitations of such data and techniques. ▸ PSI 4.2.6 Not suppress disconfirming evidence of their findings and views, and acknowledge alternative hypotheses and explanations. | O45: This is the section that separates a report from a test-results printout, and it is where most trainee reports lose marks. Anyone can list scores; the psychologist's contribution is the judgement about what they mean together. | P45: ▸ Convergence, divergence, and weighting Lay every source on one page: cognitive profile, attainment, observation, parent report, teacher report, the child's own account. Mark where they agree and where they do not. Convergence across independent sources is your strongest evidence. Divergence needs explaining — and the explanation is often the finding. Where you weight one source over another, say which and why. 'The teacher report and classroom observation converge; the parent report differs, which may reflect the different demands of the home setting' is a defensible sentence. ▸ Writing integration rather than a list The failing structure is: here are the WISC results, here are the WIAT results, here is what the teacher said. The reader is left to synthesise, and they will not. The working structure is a paragraph that begins 'Taken together, these findings indicate…' and then names the pattern, followed by a sentence naming what does not fit. If you never write a sentence containing the word 'however', you have probably smoothed something away. ▸ Not suppressing disconfirming evidence PSI clause 4.2.6 requires you not to suppress evidence that disconfirms your conclusion. In practice the suppression is rarely deliberate — you form a view early and stop noticing the data that does not fit. The countermeasure is procedural: before writing, list what your formulation does not explain. If the list is empty, you have not looked. ▸ Limitations, and why every report needs one A limitations paragraph states what the assessment did not cover and what that constrains. Typical content: domains not assessed, single-occasion data, instruments normed on other populations, information not available. It costs five minutes, it evidences CORU 1.2 and PSI 2.3.1 directly, and it is absent from most trainee reports. It is the cheapest mark in the portfolio. | Q45: ▸ PSI (2025). Code of professional ethics (5th rev.). Clauses 4.2.5 and 4.2.6. ▸ Monsen, J., & Frederickson, N. (2008). The Monsen et al. problem-analysis framework. In Frederickson, Miller & Cline (Eds.), Educational psychology. Hodder. ▸ CORU (2023). Standards of proficiency. Standards 3.4, 5.27, 5.32. | R45: ✗ Reporting test by test and calling it integration. ✗ Never writing a sentence beginning 'however'. ✗ Omitting the limitations paragraph. ✗ Weighting a source without saying you have done so. | S45: ▸ GRADE 3 You listed each test in turn. ▸ GRADE 4 An integration section exists, names convergence, and includes limitations. ▸ GRADE 5 The reader is not left to do the synthesis; divergence is named and explained. | T45: ▸ BLOCK 1 · Seeing the pattern [Habit — 30 minutes per case · Weeks 3–6 · Habit] Recognising convergence and divergence across sources rather than reporting each separately. How you build it: Lay every source on one page before writing. Mark agreements in one colour and disagreements in another. · Identify where sources converge you have it when: Convergence is stated rather than assumed [CORU SoP 3.4] · Identify where sources diverge and say so you have it when: Discrepancy is named rather than smoothed away [CORU SoP 3.4 · PSI Code 4.2.6] · Judge which source to weight and why you have it when: The weighting is defensible and written down [CORU SoP 5.32] ▸ BLOCK 2 · Writing the synthesis [Ongoing · 1–2 hours per report initially · Weeks 7–12 · Practice] Producing an integration section rather than a list of test results. How you build it: Draft one and have it torn apart in supervision. It is the hardest thing to learn from written feedback alone. · Write an integration section rather than a list you have it when: The reader is not left to do the synthesis [CORU SoP 5.27] · Ask whether the profile answers the referral question you have it when: You noticed if it did not [CORU SoP 3.4] · State what you did not assess and what that limits you have it when: A limitations paragraph exists [CORU SoP 1.2 · PSI Code 2.3.1] | U45: No full chapter yet. | V45: ▸ 1.1 Attention, concentration and work skills full entry under 1. Observation in classroom, playground and clinic ▸ 1.2 Language skills full entry under 1. Observation in classroom, playground and clinic ▸ 1.3 Comprehension and general ability full entry under 4. WISC-V administration to proficiency standard ▸ 1.4 Literacy — reading (fluency / comprehension), writing and spelling full entry under 5. WIAT administration, scoring and interpretation ▸ 1.5 Maths skills — concepts and computation full entry under 5. WIAT administration, scoring and interpretation ▸ 4.1 Friendships and social skills full entry under 8. Social communication screening measures ▸ 5.1 Vision full entry under 10. Adapt standardised procedure and record the adaptation ▸ 5.2 Hearing full entry under 10. Adapt standardised procedure and record the adaptation ▸ 5.3 Medical condition or other diagnosis full entry under 10. Adapt standardised procedure and record the adaptation | W45: Table 2 area 1 · Appendix 5 tagged Assessment · Appendix 7 observation · Table 3 tools and categories | X45: Equal Status Acts 2000–2018 — reasonable accommodation · GDPR — lawful basis, minimisation | Y45: Year 1 — Becomes the core of the Year 2 case study.
A46: SKILL | B46: 1. Assessment | C46: ▸ The reading model underneath ▸ Administering the battery ▸ Turning a profile into advice | D46: 7. Phonological and literacy measures | E46: Macro skill | F46: 7. Phonological and literacy measures | G46: Everything about this skill is on this row. Scroll right. | K46: =COUNTIF(Log!$G$3:$G$402,"7. Phonological and literacy measures") | L46: =IF(COUNTIF(Log!$G$3:$G$402,"7. Phonological and literacy measures")=0,"",SUMPRODUCT(MAX((Log!$G$3:$G$402="7. Phonological and literacy measures")*Log!$A$3:$A$402))) | M46: ▸ CORU 3.3 Be able to determine the appropriate tests/assessments required and undertake/arrange these tests ▸ CORU 5.28 Be able to critically evaluate the theory and application of a range of assessment methods used in educational psychology to identify psychological, educational and developmental needs at individual and group levels ▸ CORU 5.32 Interpret, synthesise and critically evaluate assessment data, within relevant conceptual frameworks, to inform case formulation and psychological intervention planning | N46: ▸ PSI 2.2.2 Recognise the boundaries of their competence, and do not exceed these. ▸ PSI 2.3.1 Be mindful, when making decisions based on psychological data and techniques, of the limitations of such data and techniques. | O46: Literacy referrals are the largest single category you will meet in Irish primary schools. The assessment is only useful if it leads to a specific intervention, which means you need to know both the reading model and what the schools on your patch can actually deliver. | P46: ▸ The simple view of reading Reading comprehension is the product of decoding and language comprehension — not the sum. If either is near zero, comprehension is near zero. This gives you four profiles: good decoding and good language (typical); poor decoding and good language (dyslexic profile); good decoding and poor language (poor comprehender, often missed because they read aloud fluently); poor at both (mixed). The profile determines the intervention. Phonics for a poor decoder is appropriate; phonics for a poor comprehender is a waste of the child's time. Establishing which you have is the point of the assessment. ▸ The phonological deficit hypothesis The dominant account of developmental dyslexia holds that the core difficulty is in representing and manipulating the sound structure of language, which impairs the mapping between graphemes and phonemes. Three measures are standardly taken: phonological awareness (can the child segment, blend and manipulate sounds); rapid automatised naming (how quickly can they retrieve familiar labels — a naming-speed deficit is partly separable from a phonological one); and phonological working memory (non-word repetition, digit span). The double-deficit hypothesis proposes that children weak in both phonological awareness and naming speed have the most severe difficulty — worth checking rather than assuming a single cause. ▸ Specific versus general Before concluding a specific difficulty, check the cognitive profile. A child whose reading is weak alongside generally low measured ability has a different picture from one whose reading is weak against average or above ability. Neither is more deserving of support, but they call for different interventions and different expectations. Do not write 'specific' unless you have checked. ▸ From profile to provision Write the recommendation before you look at the programme list, then check what the school holds. A structured, cumulative, multisensory phonics programme delivered four times weekly for twenty minutes by the SET, reviewed at six weeks, is a recommendation. 'Recommend phonics support' is not. Specify who, how often, how long, and when it will be reviewed. | Q46: ▸ Hulme, C., & Snowling, M. J. (2013). Developmental disorders of language learning and cognition. Wiley-Blackwell. ▸ Snowling, M. J., Hulme, C., & Nation, K. (2020). Defining and understanding dyslexia. Oxford Review of Education, 46(4), 501–513. ▸ Department of Education and Skills (2017). Continuum of Support: Guidelines for teachers. NEPS. | R46: ✗ Recommending phonics for a poor comprehender. ✗ Concluding a specific difficulty without checking the cognitive profile. ✗ Reporting composites without saying what they do and do not establish. ✗ Recommending a programme the school does not have and cannot get. | S46: ▸ GRADE 3 You named the profile without linking it to provision. ▸ GRADE 4 Battery administered and scored correctly; profile interpreted against the cognitive picture. ▸ GRADE 5 The recommendation follows visibly from the finding and the SET could start on Monday. | T46: ▸ BLOCK 1 · The reading model underneath [4–5 hours, once · Weeks 1–2 · Study] The simple view of reading, the phonological deficit hypothesis, and what a dyslexia profile actually looks like. How you build it: One chapter on reading development plus one on dyslexia. Write a half-page summary of each. · Explain why phonological awareness matters for reading you have it when: You can explain it to a teacher without notes [CORU SoP 5.12] · Distinguish a specific difficulty from a general one you have it when: You check the cognitive profile before concluding [CORU SoP 3.4 · 5.17] ▸ BLOCK 2 · Administering the battery [5–6 hours · Weeks 3–6 · Practice] CTOPP-2 or equivalent — timing, error recording, scoring the composites. How you build it: Two supervised practice administrations, then score both by hand. · Administer phonological awareness subtests to standard you have it when: Administration is fluent and timing accurate [CORU SoP 5.6] · Administer rapid naming tasks accurately you have it when: You timed and recorded errors correctly [CORU SoP 5.6] · Score the phonological composites correctly you have it when: Composites calculated and checked [CORU SoP 5.6] ▸ BLOCK 3 · Turning a profile into advice [Habit per case · Weeks 7–12 · Habit] Linking what the profile shows to an intervention the school can deliver. How you build it: Write the recommendation before you look at the programme list. Then check what is available. · Interpret a phonological profile in context you have it when: You can say what it does and does not establish [CORU SoP 5.32 · PSI Code 2.3.1] · Link the profile to what the school can deliver you have it when: The recommendation follows from the finding [CORU SoP 5.34] | U46: No full chapter yet. | V46: ▸ 1.4 Literacy — reading (fluency / comprehension), writing and spelling full entry under 5. WIAT administration, scoring and interpretation ▸ 5.2 Hearing full entry under 10. Adapt standardised procedure and record the adaptation | W46: Table 2 area 1 · Appendix 5 tagged Assessment · Appendix 7 observation · Table 3 tools and categories | X46: Equal Status Acts 2000–2018 — reasonable accommodation · GDPR — lawful basis, minimisation | Y46: Year 1 — Extends to full dyslexia assessment in Year 2.
A47: SKILL | B47: 1. Assessment | C47: ▸ Knowing what a screen is ▸ Administering and integrating ▸ Recognising atypical presentation | D47: 8. Social communication screening measures | E47: Macro skill | F47: 8. Social communication screening measures | G47: Everything about this skill is on this row. Scroll right. | K47: =COUNTIF(Log!$G$3:$G$402,"8. Social communication screening measures") | L47: =IF(COUNTIF(Log!$G$3:$G$402,"8. Social communication screening measures")=0,"",SUMPRODUCT(MAX((Log!$G$3:$G$402="8. Social communication screening measures")*Log!$A$3:$A$402))) | M47: ▸ CORU 1.2 Be able to identify the limits of their practice and know when to seek advice and additional expertise or refer to another professional ▸ CORU 5.24 Identify and apply knowledge of the intersecting forms of diversity of service users, working in an inclusive, sensitive and equitable manner ▸ CORU 5.28 Be able to critically evaluate the theory and application of a range of assessment methods used in educational psychology to identify psychological, educational and developmental needs at individual and group levels | N47: ▸ PSI 2.2.2 Recognise the boundaries of their competence, and do not exceed these. ▸ PSI 2.3.1 Be mindful, when making decisions based on psychological data and techniques, of the limitations of such data and techniques. | O47: Screening sits at a boundary you must be clear about: you are not diagnosing, and in Ireland the diagnostic pathway usually runs through a Children's Disability Network Team. Being precise about what a screen entitles you to say protects the child from a premature label and protects you from practising outside competence. | P47: ▸ Screening, assessment, diagnosis — three different things A screen is a brief instrument designed to sort a population into probably-worth-looking-at and probably-not. It is optimised for sensitivity at the cost of specificity, which means false positives are expected and acceptable. An assessment is a fuller individual investigation. A diagnosis is a formal determination against criteria (DSM-5-TR or ICD-11), usually multidisciplinary for autism. A positive screen entitles you to write: this child's presentation warrants further assessment, and here is the pathway. It does not entitle you to write that the child is autistic, and you should say so explicitly in the report. ▸ What the common instruments do The SCQ is a 40-item parent questionnaire derived from the ADI-R, with a commonly used cut-off around 15, though the manual's guidance and local practice vary. The SRS-2 gives a dimensional measure of social responsiveness rather than a yes/no, which is often more useful clinically. Neither is diagnostic. Both rely on a single informant's recall, which is their main weakness. ▸ Why questionnaires and observation disagree A parent reports across years and settings; you observe for forty minutes in one. Disagreement is normal and informative. If the screen is positive and you saw nothing, consider: masking, a structured setting that supports the child, or a parent reporting anxiety-driven behaviour that has a different source. If the screen is negative and you saw a great deal, consider a parent without a comparison point, or behaviour specific to the school context. Report the disagreement rather than choosing a side. ▸ Atypical and masked presentation Autistic girls are identified later and less often, and the reasons are partly instrumental — the screening items were normed on samples that were predominantly male. Presentations that are commonly missed include: social difficulty that looks like shyness or anxiety; intense interests in socially typical topics; and camouflaging, where the child consciously imitates peers and is exhausted by it. A negative screen in a girl with a strong parental concern is a reason to look further, not to stop. The same logic applies to late identification in children whose difficulty was previously attributed to something else. | Q47: ▸ Rutter, M., Bailey, A., & Lord, C. (2003). Social Communication Questionnaire manual. Western Psychological Services. ▸ Psychological Society of Ireland (2022). Guidelines for psychologists working with autistic people. ▸ Lai, M.-C., & Baron-Cohen, S. (2015). Identifying the lost generation of adults with autism spectrum conditions. The Lancet Psychiatry, 2(11), 1013–1027. ▸ HSE (2023). Progressing Disability Services: CDNT referral pathways. — know the local route. | R47: ✗ Writing anything that reads as a diagnosis. ✗ Relying on the questionnaire alone. ✗ Treating a negative screen as reassurance when parental concern is strong. ✗ Not knowing where a positive screen goes next in this service. | S47: ▸ GRADE 3 You administered it and reported the result. ▸ GRADE 4 Screen integrated with observation; limits stated; pathway named. ▸ GRADE 5 You wrote that a screen is not a diagnosis, considered masked presentation, and the family left knowing the next step. | T47: ▸ BLOCK 1 · Knowing what a screen is [4–5 hours, once · Weeks 1–2 · Study] The difference between screening, assessment and diagnosis, and what a positive screen entitles you to say. How you build it: Read the SCQ manual's validity section. Then read the PSI Autism Guidelines 2022. · Recognise the limits of a screening instrument you have it when: You said in writing that a screen is not a diagnosis [CORU SoP 1.2 · PSI Code 2.3.1] · Know the onward diagnostic pathway in this service you have it when: You could name where a positive screen goes [CORU SoP 1.2] ▸ BLOCK 2 · Administering and integrating [3–4 hours · Weeks 7–12 · Practice] Completing the screen with an informant and combining it with observation. How you build it: Complete three with parents, then compare each with your own observation. · Administer a screen with a parent you have it when: You explained what a screen can and cannot tell them [CORU SoP 2.1] · Integrate screening data with direct observation you have it when: You did not rely on the questionnaire alone [CORU SoP 3.4] ▸ BLOCK 3 · Recognising atypical presentation [3 hours, once · Weeks 3–6 · Study] How autism presents differently in girls, in late identification, and alongside anxiety. How you build it: Read one paper on female presentation. It changes what you notice permanently. · Recognise masked or atypical presentation you have it when: You considered presentation in girls and late identification [CORU SoP 5.24 · PSI Autism Guidelines 2022] | U47: No full chapter yet. | V47: ▸ 4.1 Friendships and social skills FULL ENTRY HERE | W47: Table 2 area 1 · Appendix 5 tagged Assessment · Appendix 7 observation · Table 3 tools and categories | X47: Equal Status Acts 2000–2018 — reasonable accommodation · GDPR — lawful basis, minimisation | Y47: Year 1 — Extends to ADOS/ADI-R observation in diagnostic settings in Year 2.
A48: AREA | B48: 1. Assessment | D48: 8. Social communication screening measures | E48: Referral area | F48: 4.1 Friendships and social skills | G48: ON THE FORM — Section 5 | K48: =COUNTIF(Log!$E$3:$E$402,"4.1 Friendships and social skills") | L48: =IF(COUNTIF(Log!$E$3:$E$402,"4.1 Friendships and social skills")=0,"",SUMPRODUCT(MAX((Log!$E$3:$E$402="4.1 Friendships and social skills")*Log!$A$3:$A$402))) | M48: DIAGNOSES ▸ Autism Spectrum Disorder — level 1, requiring support DSM-5-TR / ICD-11 6A02 ▸ Autism Spectrum Disorder — level 2, requiring substantial support DSM-5-TR / ICD-11 6A02 ▸ Autism Spectrum Disorder — level 3, requiring very substantial support DSM-5-TR / ICD-11 6A02 ▸ ASD with accompanying intellectual impairment DSM-5-TR specifier ▸ ASD with accompanying language impairment DSM-5-TR specifier ▸ Social (Pragmatic) Communication Disorder DSM-5-TR / ICD-11 6A01 | N48: PRESENTATIONS WITH NO DIAGNOSIS ▸ Pathological Demand Avoidance (PDA) profile Not a DSM diagnosis ▸ Peer relationship difficulties and social isolation Not a DSM diagnosis ▸ Bullying Not a DSM diagnosis ▸ Social adaptive skills Not a DSM diagnosis ▸ Co-operation with peers in group work Added — Form 2 survey wording ▸ Turn-taking and shared play Added ▸ Reading social cues and repair after conflict Added ▸ Masking and the cost of it Added ▸ Loneliness without observable difficulty Added — the quiet ones get missed | O48: REFER TO ▸ CDNT ▸ NEPS for school supports ▸ NEPS ▸ NEPS with SLT ▸ whole-school policy support | P48: — | Q48: ▸ Early Years / Pre-School (0–5) Play observation · ADOS-2 Toddler/Module 1 via CDNT · parent developmental history · SCQ · AIM and preschool staff consultation. | R48: ▸ School Age (6–12) Yard and classroom observation · SRS-2 parent and teacher (your named development area) · SCQ · ADOS-2 via team · sociometric mapping · friendship interview with the pupil. | S48: ▸ Adolescent (13–16) SRS-2 including self-report where available · ADOS-2 Module 3/4 via team · self-report on friendship and belonging · social demands of post-primary are different — assess those, not primary ones. | T48: ▸ Young Adult (17–26) AQ-10 / adult screening · functional social demands of course or work · adult diagnostic services. | U48: ▸ Special Setting (class or school) Social opportunity within the setting · integration arrangements · peer group available to the pupil. | AG48: Environmental Factors — Family, School, Community · Family dynamics (including CEC, adopted and CYP with SGOs) · Siblings, extended family, links and relationship to school and education · Family stressors · Financial stress · Housing · Home learning environment · Parental attitude to school/education · Trauma/significant life events · Adverse childhood events · Family views · Bereavements/relational losses · Key adults / members of staff (significant relationships both positive and negative in and out of school) and level of school commitment to child · Travel distance to school · School attendance · Child's views/preferences · School-parent relationship · Peer group dynamics · School learning environment · Access to interventions and support · Curriculum/exam boards · Teacher expectations · Teacher/staff understanding/knowledge · Attainment-based grouping · Influences in school and the local community · Other agency involvement — Police, YOT, CAMHS, Speech and Language Service, Fair Access, SENAT, Virtual School, SGO Advisor, Intensive Planning Team, Prevent, CSE, Early Years, School Nurse, Portage, Early Help, Social and Caring Services Health Services | AH48: Within-Child — Biological Factors · Family history including early development, physical development, medical conditions and diagnoses/difficulties · General health · Medication · Dietary needs · Sensory needs · Addictions e.g. smoking, drink, drugs | AI48: Within-Child — Cognitive Factors ASSESSABLE · Memory · Language · Executive functioning: including emotional and behavioural regulation/development · Attention and concentration · Visual spatial ability · Phonological processing · Processing speed · Non-verbal reasoning · Verbal ability (e.g. word problems, verbal presentation) · Logical reasoning ability · Literacy skills · Attainment OBSERVATION AND CONSULTATION · Signs of developmental trauma impacting on ability to participate in learning · Ability to problem-solve · Flexibility of thought and action · Self-awareness | AJ48: Within-Child — Affective Factors · Experience of developmental trauma · Confidence · Self-esteem · Emotional understanding and expression · Sense of enablement · Sense of self · Sense of belonging · Motivation (intrinsic or extrinsic) · Resiliency · Mood · Anxiety · Aspirations · Perseverance / determination · Sense of humour · Self-control · Social skills · Empathy | AK48: Within-Child — Behavioural Factors · Ability to develop and maintain friendships and relationships · Positive achievements · Care/concern for others, volunteering, helping · Dangerous or risk-taking behaviour · Verbal / physical abuse · Self-harm · Bullying · Truancy
A49: SKILL | B49: 1. Assessment | C49: ▸ Choosing the instrument ▸ Administering and scoring ▸ Reading discrepancy | D49: 9. Behavioural and emotional rating scales | E49: Macro skill | F49: 9. Behavioural and emotional rating scales | G49: Everything about this skill is on this row. Scroll right. | K49: =COUNTIF(Log!$G$3:$G$402,"9. Behavioural and emotional rating scales") | L49: =IF(COUNTIF(Log!$G$3:$G$402,"9. Behavioural and emotional rating scales")=0,"",SUMPRODUCT(MAX((Log!$G$3:$G$402="9. Behavioural and emotional rating scales")*Log!$A$3:$A$402))) | M49: ▸ CORU 3.3 Be able to determine the appropriate tests/assessments required and undertake/arrange these tests ▸ CORU 3.4 Be able to analyse and critically evaluate the information collected in the assessment process ▸ CORU 5.32 Interpret, synthesise and critically evaluate assessment data, within relevant conceptual frameworks, to inform case formulation and psychological intervention planning | N49: ▸ PSI 2.2.2 Recognise the boundaries of their competence, and do not exceed these. ▸ PSI 2.3.1 Be mindful, when making decisions based on psychological data and techniques, of the limitations of such data and techniques. ▸ PSI 4.2.2 Take due care to avoid misrepresentation, exaggeration, distortion or errors in reporting assessment results, research findings or service effectiveness, and act quickly to correct any such error. | O49: Rating scales give you something no other method does: the same construct measured by two people who see the child in different settings. The disagreement between them is usually more informative than either score alone, and it is routinely thrown away. | P49: ▸ What the common instruments are The SDQ is brief, free, widely used in Ireland, with parent, teacher and self-report versions covering emotional symptoms, conduct, hyperactivity, peer problems and prosocial behaviour plus an impact supplement. The Conners forms focus on attention and hyperactivity. The BASC-3 and ASEBA are broader and longer. Choose for the question: the SDQ for a general screen, a focused instrument where the referral is specific. ▸ Elevated versus clinically significant Standardised scores are usually banded — average, slightly raised, high, very high — with the bands set by percentile in the norm sample. An elevated score means unusual relative to the norm group. It does not mean disordered, and it does not license a diagnosis. Say which band and what it means in plain words, and avoid reporting a T-score without translating it. ▸ Reading informant discrepancy Cross-informant agreement on child behaviour is modest — correlations around 0.3 to 0.4 between parents and teachers are typical. This is not measurement failure; it reflects genuine setting specificity. A child rated high at home and average at school may be managing all day and releasing afterwards, or may be supported well at school. A child rated high at school and average at home may face demands at school that are not present at home. Both patterns are findings. Report them as information about context, not as one informant being wrong. ▸ The child's own voice Self-report versions exist from around age 11 for the SDQ and younger for some instruments. The child's own account is required by CORU 2.3 and by Article 12 of the UNCRC, and it frequently diverges from both adults. Where a self-report is not age-appropriate, you still need the child's view — obtained in conversation and quoted directly in the report. | Q49: ▸ Goodman, R. (2001). Psychometric properties of the Strengths and Difficulties Questionnaire. Journal of the American Academy of Child and Adolescent Psychiatry, 40(11), 1337–1345. ▸ De Los Reyes, A., et al. (2015). The validity of the multi-informant approach to assessing child and adolescent mental health. Psychological Bulletin, 141(4), 858–900. ▸ United Nations (1989). Convention on the Rights of the Child, Article 12. | R49: ✗ Reporting a T-score without translating it. ✗ Treating an elevated score as a diagnosis. ✗ Averaging informants, which destroys the most useful finding. ✗ Omitting the child's self-report where one was available. | S49: ▸ GRADE 3 You reported both informants separately. ▸ GRADE 4 Correct instrument, correct scoring, bands translated into plain words. ▸ GRADE 5 Discrepancy treated as data about context, and the child's own account included. | T49: ▸ BLOCK 1 · Choosing the instrument [3 hours, once · Weeks 1–2 · Study] Which scale for which question, which informants, and what each is normed on. How you build it: Compare SDQ, Conners' and ASEBA on one page. Know what each is for. · Select the right forms for informant and age you have it when: Parent, teacher and self-report chosen appropriately [CORU SoP 3.3] · Include the child's own self-report where age-appropriate you have it when: The child's account appears alongside the adults' [UNCRC Art. 12 · CORU SoP 2.3] ▸ BLOCK 2 · Administering and scoring [3–4 hours · Weeks 3–6 · Practice] Briefing informants, chasing returns, scoring and converting. How you build it: Do three sets. Score by hand once. · Explain to informants how to complete them you have it when: Forms come back usable [CORU SoP 2.1] · Score and convert to standardised scores you have it when: Scoring is checked [CORU SoP 5.6] ▸ BLOCK 3 · Reading discrepancy [Ongoing · Weeks 7–12 · Practice] What it means when parent and teacher disagree, and why that is data rather than error. How you build it: Bring one discrepant set to supervision and be talked through it. · Analyse informant agreement and discrepancy you have it when: Discrepancy treated as data about context [CORU SoP 3.4 · 5.32] · Distinguish elevated from clinically significant you have it when: You know what the cut-offs mean and say so [PSI Code 4.2.2] | U49: No full chapter yet. | V49: ▸ 1.1 Attention, concentration and work skills full entry under 1. Observation in classroom, playground and clinic ▸ 2.1 Behaviour in class full entry under 1. Observation in classroom, playground and clinic ▸ 2.2 Behaviour during break times and around the school full entry under 1. Observation in classroom, playground and clinic ▸ 3.1 Confidence and self-esteem FULL ENTRY HERE ▸ 3.2 Anxiety FULL ENTRY HERE ▸ 3.3 Obsessive-compulsive and related FULL ENTRY HERE ▸ 3.4 Mood FULL ENTRY HERE ▸ 4.1 Friendships and social skills full entry under 8. Social communication screening measures | W49: Table 2 area 1 · Appendix 5 tagged Assessment · Appendix 7 observation · Table 3 tools and categories | X49: Equal Status Acts 2000–2018 — reasonable accommodation · GDPR — lawful basis, minimisation · UNCRC Art. 12 | Y49: Year 1 — Extends to structured diagnostic interviewing in Year 2.
A50: AREA | B50: 1. Assessment | D50: 9. Behavioural and emotional rating scales | E50: Referral area | F50: 3.1 Confidence and self-esteem | G50: ON THE FORM — Section 5 | K50: =COUNTIF(Log!$E$3:$E$402,"3.1 Confidence and self-esteem") | L50: =IF(COUNTIF(Log!$E$3:$E$402,"3.1 Confidence and self-esteem")=0,"",SUMPRODUCT(MAX((Log!$E$3:$E$402="3.1 Confidence and self-esteem")*Log!$A$3:$A$402))) | M50: No diagnoses. Everything here is a presentation. | N50: PRESENTATIONS WITH NO DIAGNOSIS ▸ Low confidence and self-esteem Not a DSM diagnosis ▸ Learned helplessness Not a DSM diagnosis ▸ Academic self-concept vs global self-esteem Added ▸ Attribution style — effort vs ability Added ▸ Response to failure and setback Added — Form 2 survey wording ▸ Perfectionism and fear of getting it wrong Added ▸ Self-esteem as a consequence of unidentified SLD Added — check the sequence | O50: REFER TO ▸ NEPS | P50: — | Q50: ▸ Early Years / Pre-School (0–5) Adult report only · structured play and comment · no self-report measure is valid at this age. | R50: ▸ School Age (6–12) Pupil self-report: My Thoughts About School (NEPS Continuum of Support) · Piers-Harris 3 · drawing and sentence-completion · teacher and parent report. | S50: ▸ Adolescent (13–16) Self-report measures become the primary source · Piers-Harris 3 · BASC-3 SRP · solution-focused interview · watch for low mood underneath. | T50: ▸ Young Adult (17–26) Self-report interview · course or work identity · less likely a NEPS referral. | U50: ▸ Special Setting (class or school) Self-concept relative to the setting peer group, not the mainstream one. | AG50: Environmental Factors — Family, School, Community · Family dynamics (including CEC, adopted and CYP with SGOs) · Siblings, extended family, links and relationship to school and education · Family stressors · Financial stress · Housing · Home learning environment · Parental attitude to school/education · Trauma/significant life events · Adverse childhood events · Family views · Bereavements/relational losses · Key adults / members of staff (significant relationships both positive and negative in and out of school) and level of school commitment to child · Travel distance to school · School attendance · Child's views/preferences · School-parent relationship · Peer group dynamics · School learning environment · Access to interventions and support · Curriculum/exam boards · Teacher expectations · Teacher/staff understanding/knowledge · Attainment-based grouping · Influences in school and the local community · Other agency involvement — Police, YOT, CAMHS, Speech and Language Service, Fair Access, SENAT, Virtual School, SGO Advisor, Intensive Planning Team, Prevent, CSE, Early Years, School Nurse, Portage, Early Help, Social and Caring Services Health Services | AH50: Within-Child — Biological Factors · Family history including early development, physical development, medical conditions and diagnoses/difficulties · General health · Medication · Dietary needs · Sensory needs · Addictions e.g. smoking, drink, drugs | AI50: Within-Child — Cognitive Factors ASSESSABLE · Memory · Language · Executive functioning: including emotional and behavioural regulation/development · Attention and concentration · Visual spatial ability · Phonological processing · Processing speed · Non-verbal reasoning · Verbal ability (e.g. word problems, verbal presentation) · Logical reasoning ability · Literacy skills · Attainment OBSERVATION AND CONSULTATION · Signs of developmental trauma impacting on ability to participate in learning · Ability to problem-solve · Flexibility of thought and action · Self-awareness | AJ50: Within-Child — Affective Factors · Experience of developmental trauma · Confidence · Self-esteem · Emotional understanding and expression · Sense of enablement · Sense of self · Sense of belonging · Motivation (intrinsic or extrinsic) · Resiliency · Mood · Anxiety · Aspirations · Perseverance / determination · Sense of humour · Self-control · Social skills · Empathy | AK50: Within-Child — Behavioural Factors · Ability to develop and maintain friendships and relationships · Positive achievements · Care/concern for others, volunteering, helping · Dangerous or risk-taking behaviour · Verbal / physical abuse · Self-harm · Bullying · Truancy
A51: AREA | B51: 1. Assessment | D51: 9. Behavioural and emotional rating scales | E51: Referral area | F51: 3.2 Anxiety | G51: ADDED — implied by the form | K51: =COUNTIF(Log!$E$3:$E$402,"3.2 Anxiety") | L51: =IF(COUNTIF(Log!$E$3:$E$402,"3.2 Anxiety")=0,"",SUMPRODUCT(MAX((Log!$E$3:$E$402="3.2 Anxiety")*Log!$A$3:$A$402))) | M51: DIAGNOSES ▸ Separation Anxiety Disorder DSM-5-TR / ICD-11 6B00–6B0Z ▸ Social Anxiety Disorder (social phobia) DSM-5-TR / ICD-11 6B00–6B0Z ▸ Generalised Anxiety Disorder DSM-5-TR / ICD-11 6B00–6B0Z ▸ Specific Phobia DSM-5-TR / ICD-11 6B00–6B0Z ▸ Panic Disorder DSM-5-TR / ICD-11 6B00–6B0Z ▸ Agoraphobia DSM-5-TR / ICD-11 6B00–6B0Z ▸ Selective mutism DSM-5-TR anxiety ▸ Other specified / unspecified anxiety disorder DSM-5-TR | N51: PRESENTATIONS WITH NO DIAGNOSIS ▸ School anxiety presentations (not a standalone diagnosis) Not a DSM diagnosis ▸ Test and exam anxiety Added ▸ Performance anxiety in oral work Added ▸ Anticipatory anxiety about transitions Added ▸ Somatic complaints presenting at school (tummy aches, headaches) Added ▸ Anxiety secondary to an unmet learning need Added | O51: REFER TO ▸ Primary Care (mild–mod) ▸ CAMHS (severe) ▸ Primary Care ▸ CAMHS ▸ CAMHS — also under 1.2 ▸ NEPS ▸ GP to rule out | P51: — | Q51: ▸ Early Years / Pre-School (0–5) Parent and staff report · separation at drop-off is the common presentation · no self-report measure · Primary Care rather than NEPS for clinical anxiety. | R51: ▸ School Age (6–12) RCADS parent and child · SCAS · pupil interview using drawing or scaling · classroom observation at the anxious moment, not a random moment. | S51: ▸ Adolescent (13–16) RCADS self-report · SCAS-A · Beck Youth Inventories · direct interview · school attendance data alongside — anxiety and EBSA travel together. | T51: ▸ Young Adult (17–26) Self-report · course and workplace demands · refer to adult mental health rather than hold. | U51: ▸ Special Setting (class or school) Anxiety about the setting or about transition out of it · staff report on where and when. | AG51: Environmental Factors — Family, School, Community · Family dynamics (including CEC, adopted and CYP with SGOs) · Siblings, extended family, links and relationship to school and education · Family stressors · Financial stress · Housing · Home learning environment · Parental attitude to school/education · Trauma/significant life events · Adverse childhood events · Family views · Bereavements/relational losses · Key adults / members of staff (significant relationships both positive and negative in and out of school) and level of school commitment to child · Travel distance to school · School attendance · Child's views/preferences · School-parent relationship · Peer group dynamics · School learning environment · Access to interventions and support · Curriculum/exam boards · Teacher expectations · Teacher/staff understanding/knowledge · Attainment-based grouping · Influences in school and the local community · Other agency involvement — Police, YOT, CAMHS, Speech and Language Service, Fair Access, SENAT, Virtual School, SGO Advisor, Intensive Planning Team, Prevent, CSE, Early Years, School Nurse, Portage, Early Help, Social and Caring Services Health Services | AH51: Within-Child — Biological Factors · Family history including early development, physical development, medical conditions and diagnoses/difficulties · General health · Medication · Dietary needs · Sensory needs · Addictions e.g. smoking, drink, drugs | AI51: Within-Child — Cognitive Factors ASSESSABLE · Memory · Language · Executive functioning: including emotional and behavioural regulation/development · Attention and concentration · Visual spatial ability · Phonological processing · Processing speed · Non-verbal reasoning · Verbal ability (e.g. word problems, verbal presentation) · Logical reasoning ability · Literacy skills · Attainment OBSERVATION AND CONSULTATION · Signs of developmental trauma impacting on ability to participate in learning · Ability to problem-solve · Flexibility of thought and action · Self-awareness | AJ51: Within-Child — Affective Factors · Experience of developmental trauma · Confidence · Self-esteem · Emotional understanding and expression · Sense of enablement · Sense of self · Sense of belonging · Motivation (intrinsic or extrinsic) · Resiliency · Mood · Anxiety · Aspirations · Perseverance / determination · Sense of humour · Self-control · Social skills · Empathy | AK51: Within-Child — Behavioural Factors · Ability to develop and maintain friendships and relationships · Positive achievements · Care/concern for others, volunteering, helping · Dangerous or risk-taking behaviour · Verbal / physical abuse · Self-harm · Bullying · Truancy
A52: AREA | B52: 1. Assessment | D52: 9. Behavioural and emotional rating scales | E52: Referral area | F52: 3.3 Obsessive-compulsive and related | G52: ADDED — implied by the form | K52: =COUNTIF(Log!$E$3:$E$402,"3.3 Obsessive-compulsive and related") | L52: =IF(COUNTIF(Log!$E$3:$E$402,"3.3 Obsessive-compulsive and related")=0,"",SUMPRODUCT(MAX((Log!$E$3:$E$402="3.3 Obsessive-compulsive and related")*Log!$A$3:$A$402))) | M52: DIAGNOSES ▸ Obsessive-Compulsive Disorder DSM-5-TR / ICD-11 6B20–6B2Z ▸ Body Dysmorphic Disorder DSM-5-TR / ICD-11 6B20–6B2Z ▸ Hoarding Disorder DSM-5-TR / ICD-11 6B20–6B2Z ▸ Trichotillomania (hair-pulling) DSM-5-TR / ICD-11 6B20–6B2Z ▸ Excoriation (skin-picking) Disorder DSM-5-TR / ICD-11 6B20–6B2Z | N52: PRESENTATIONS WITH NO DIAGNOSIS ▸ Rigidity and routine that is not OCD Added — check autism first ▸ Repeated checking of work Added ▸ Ritual at transitions Added | O52: REFER TO ▸ Primary Care ▸ CAMHS (severe) ▸ CAMHS ▸ NEPS | P52: — | Q52: ▸ Early Years / Pre-School (0–5) Rarely identified at this age · parent report · routines are developmentally normal here. | R52: ▸ School Age (6–12) Parent and teacher report · CY-BOCS via clinical services, not NEPS · your job is to describe school impact and refer. | S52: ▸ Adolescent (13–16) Self-report emerges · CY-BOCS via CAMHS · describe impact on work completion and attendance. | T52: ▸ Young Adult (17–26) Adult services. | U52: ▸ Special Setting (class or school) Distinguish autistic routine from compulsion — the function differs. | AG52: Environmental Factors — Family, School, Community · Family dynamics (including CEC, adopted and CYP with SGOs) · Siblings, extended family, links and relationship to school and education · Family stressors · Financial stress · Housing · Home learning environment · Parental attitude to school/education · Trauma/significant life events · Adverse childhood events · Family views · Bereavements/relational losses · Key adults / members of staff (significant relationships both positive and negative in and out of school) and level of school commitment to child · Travel distance to school · School attendance · Child's views/preferences · School-parent relationship · Peer group dynamics · School learning environment · Access to interventions and support · Curriculum/exam boards · Teacher expectations · Teacher/staff understanding/knowledge · Attainment-based grouping · Influences in school and the local community · Other agency involvement — Police, YOT, CAMHS, Speech and Language Service, Fair Access, SENAT, Virtual School, SGO Advisor, Intensive Planning Team, Prevent, CSE, Early Years, School Nurse, Portage, Early Help, Social and Caring Services Health Services | AH52: Within-Child — Biological Factors · Family history including early development, physical development, medical conditions and diagnoses/difficulties · General health · Medication · Dietary needs · Sensory needs · Addictions e.g. smoking, drink, drugs | AI52: Within-Child — Cognitive Factors ASSESSABLE · Memory · Language · Executive functioning: including emotional and behavioural regulation/development · Attention and concentration · Visual spatial ability · Phonological processing · Processing speed · Non-verbal reasoning · Verbal ability (e.g. word problems, verbal presentation) · Logical reasoning ability · Literacy skills · Attainment OBSERVATION AND CONSULTATION · Signs of developmental trauma impacting on ability to participate in learning · Ability to problem-solve · Flexibility of thought and action · Self-awareness | AJ52: Within-Child — Affective Factors · Experience of developmental trauma · Confidence · Self-esteem · Emotional understanding and expression · Sense of enablement · Sense of self · Sense of belonging · Motivation (intrinsic or extrinsic) · Resiliency · Mood · Anxiety · Aspirations · Perseverance / determination · Sense of humour · Self-control · Social skills · Empathy | AK52: Within-Child — Behavioural Factors · Ability to develop and maintain friendships and relationships · Positive achievements · Care/concern for others, volunteering, helping · Dangerous or risk-taking behaviour · Verbal / physical abuse · Self-harm · Bullying · Truancy
A53: AREA | B53: 1. Assessment | D53: 9. Behavioural and emotional rating scales | E53: Referral area | F53: 3.4 Mood | G53: ADDED — implied by the form | K53: =COUNTIF(Log!$E$3:$E$402,"3.4 Mood") | L53: =IF(COUNTIF(Log!$E$3:$E$402,"3.4 Mood")=0,"",SUMPRODUCT(MAX((Log!$E$3:$E$402="3.4 Mood")*Log!$A$3:$A$402))) | M53: DIAGNOSES ▸ Major Depressive Disorder — single episode DSM-5-TR / ICD-11 6A70–6A7Z ▸ Major Depressive Disorder — recurrent episode DSM-5-TR / ICD-11 6A70–6A7Z ▸ Persistent Depressive Disorder (dysthymia) DSM-5-TR / ICD-11 6A70–6A7Z ▸ Premenstrual Dysphoric Disorder DSM-5-TR / ICD-11 6A70–6A7Z ▸ Other specified / unspecified depressive disorder DSM-5-TR | N53: PRESENTATIONS WITH NO DIAGNOSIS ▸ Low mood without diagnostic threshold Added ▸ Loss of interest in school activities previously enjoyed Added ▸ Withdrawal from peers Added ▸ Irritability as the presentation of low mood in young people Added | O53: REFER TO ▸ CAMHS (mod–severe) ▸ Primary Care (mild–mod) ▸ CAMHS ▸ Primary Care ▸ NEPS | P53: — | Q53: ▸ Early Years / Pre-School (0–5) Not assessed at this age · parent report on mood and play · refer. | R53: ▸ School Age (6–12) Parent and teacher report · pupil interview · MFQ · low mood often presents as irritability or refusal rather than sadness. | S53: ▸ Adolescent (13–16) MFQ self-report · Beck Youth Inventories · direct interview · always screen for risk — see 3.7 · attendance and engagement data. | T53: ▸ Young Adult (17–26) Adult services. | U53: ▸ Special Setting (class or school) Mood against the setting baseline · staff who know the pupil best. | AG53: Environmental Factors — Family, School, Community · Family dynamics (including CEC, adopted and CYP with SGOs) · Siblings, extended family, links and relationship to school and education · Family stressors · Financial stress · Housing · Home learning environment · Parental attitude to school/education · Trauma/significant life events · Adverse childhood events · Family views · Bereavements/relational losses · Key adults / members of staff (significant relationships both positive and negative in and out of school) and level of school commitment to child · Travel distance to school · School attendance · Child's views/preferences · School-parent relationship · Peer group dynamics · School learning environment · Access to interventions and support · Curriculum/exam boards · Teacher expectations · Teacher/staff understanding/knowledge · Attainment-based grouping · Influences in school and the local community · Other agency involvement — Police, YOT, CAMHS, Speech and Language Service, Fair Access, SENAT, Virtual School, SGO Advisor, Intensive Planning Team, Prevent, CSE, Early Years, School Nurse, Portage, Early Help, Social and Caring Services Health Services | AH53: Within-Child — Biological Factors · Family history including early development, physical development, medical conditions and diagnoses/difficulties · General health · Medication · Dietary needs · Sensory needs · Addictions e.g. smoking, drink, drugs | AI53: Within-Child — Cognitive Factors ASSESSABLE · Memory · Language · Executive functioning: including emotional and behavioural regulation/development · Attention and concentration · Visual spatial ability · Phonological processing · Processing speed · Non-verbal reasoning · Verbal ability (e.g. word problems, verbal presentation) · Logical reasoning ability · Literacy skills · Attainment OBSERVATION AND CONSULTATION · Signs of developmental trauma impacting on ability to participate in learning · Ability to problem-solve · Flexibility of thought and action · Self-awareness | AJ53: Within-Child — Affective Factors · Experience of developmental trauma · Confidence · Self-esteem · Emotional understanding and expression · Sense of enablement · Sense of self · Sense of belonging · Motivation (intrinsic or extrinsic) · Resiliency · Mood · Anxiety · Aspirations · Perseverance / determination · Sense of humour · Self-control · Social skills · Empathy | AK53: Within-Child — Behavioural Factors · Ability to develop and maintain friendships and relationships · Positive achievements · Care/concern for others, volunteering, helping · Dangerous or risk-taking behaviour · Verbal / physical abuse · Self-harm · Bullying · Truancy
A54: SKILL | B54: 1. Assessment | C54: ▸ Knowing what adaptation costs ▸ Noticing and deciding in the moment | D54: 10. Adapt standardised procedure and record the adaptation | E54: Macro skill | F54: 10. Adapt standardised procedure and record the adaptation | G54: Everything about this skill is on this row. Scroll right. | K54: =COUNTIF(Log!$G$3:$G$402,"10. Adapt standardised procedure and record the adaptation") | L54: =IF(COUNTIF(Log!$G$3:$G$402,"10. Adapt standardised procedure and record the adaptation")=0,"",SUMPRODUCT(MAX((Log!$G$3:$G$402="10. Adapt standardised procedure and record the adaptation")*Log!$A$3:$A$402))) | M54: ▸ CORU 2.8 Be able to produce clear, concise, accurate and objective documentation ▸ CORU 5.31 Conduct a range of assessment methods safely and ethically, adapting and re-evaluating their application as appropriate | N54: ▸ PSI 2.3.3 Terminate an activity when it is clear the activity is more harmful than beneficial, or when it is no longer needed. ▸ PSI 4.2.2 Take due care to avoid misrepresentation, exaggeration, distortion or errors in reporting assessment results, research findings or service effectiveness, and act quickly to correct any such error. | O54: Standardisation is what makes a norm-referenced score meaningful, and rigid adherence can make the assessment meaningless for the child in front of you. Knowing which adaptations preserve validity and which destroy it — and recording either honestly — is a genuine competency, not a workaround. | P54: ▸ What standardisation buys you, and what it costs A standard score compares this child to a norm sample tested under specified conditions. Change the conditions and the comparison weakens. That is the cost of adaptation. The benefit is that a child who cannot access the task under standard conditions produces a score that measures their access, not their ability. Both errors are real; the judgement is which one you are making. ▸ Adaptations that preserve the comparison, and those that do not Generally preserving: a break between subtests; repeating an instruction where the manual permits; adjusting the physical environment (lighting, seating, noise); allowing a fidget object; moving to a different room. Generally compromising: extending a timed item; rephrasing an instruction in your own words; providing a prompt the manual does not permit; changing item order within a subtest. Where an adaptation compromises the comparison, you may still make it — but the score is then descriptive rather than normative, and you must say so. This is a general principle rather than a rule to apply blindly: check the specific manual, and if a given adaptation is not addressed there, take it to supervision rather than deciding alone. ▸ Reasonable accommodation as a legal duty Under the Equal Status Acts 2000–2018 a service provider must do all that is reasonable to accommodate a person with a disability. That duty applies to your assessment. It does not oblige you to produce a valid standard score by any means — it obliges you to make the assessment accessible, and to be honest about what the resulting score means. ▸ Recording, and why it must be contemporaneous Annotate the protocol at the moment the adaptation happens, not afterwards. Write what you did, when, and why. Then in the report state the adaptation and its effect on interpretation: 'Two breaks were taken at the child's request. Standardised timing was preserved and scores are considered valid.' Or where it was not preserved: 'Instructions for Block Design were rephrased. This departs from standard procedure and the score is reported descriptively rather than as a normative comparison.' Written a week later, the same sentence is a reconstruction. ▸ Being willing to stop PSI clause 2.3.3 requires terminating an activity that is more harmful than beneficial. An assessment that is distressing a child and producing invalid data meets that test. Stopping is a defensible professional decision; continuing to get a complete protocol is not. Record the decision and the reason. | Q54: ▸ Equal Status Acts 2000–2018. — the reasonable accommodation provisions. ▸ PSI (2025). Code of professional ethics (5th rev.). Clauses 2.3.3 and 4.2.2. ▸ Wechsler, D. (2016). WISC-V UK administration and scoring manual. Pearson. — the section on testing the limits. ▸ CORU (2023). Standards of proficiency. Standards 5.31, 2.8. | R54: ✗ Adapting and not recording it. ✗ Recording it afterwards from memory. ✗ Reporting an adapted score as if it were normative. ✗ Pushing through distress to complete the protocol. ✗ Deciding alone on an adaptation the manual does not address. | S54: ▸ GRADE 3 You adapted, but wrote it up afterwards. ▸ GRADE 4 Adaptation chosen proportionately, annotated at the time, effect on validity stated. ▸ GRADE 5 You were willing to stop, and said so in writing. | T54: ▸ BLOCK 1 · Knowing what adaptation costs [2–3 hours, once · Weeks 1–2 · Study] Which adaptations preserve validity, which invalidate a score, and how the manual treats each. How you build it: Ask your supervisor for three examples and why. Read the manual's section on testing the limits. · Choose an adaptation proportionate to the need you have it when: Break, rephrase, reorder or discontinue, chosen deliberately [CORU SoP 5.31 · Equal Status Acts] · State the effect on validity in the report you have it when: You said whether scores remain interpretable [PSI Code 4.2.2] ▸ BLOCK 2 · Noticing and deciding in the moment [Builds with practice · Weeks 7–12 · Practice] Recognising when standard procedure has stopped working, and being willing to stop entirely. How you build it: Write a note after every administration on what you noticed and when. · Recognise when standard procedure is not working you have it when: You noticed early rather than at the end [CORU SoP 5.31] · Record the adaptation at the moment it happens you have it when: Annotated on the protocol, not reconstructed [CORU SoP 2.8] · Re-evaluate whether to continue at all you have it when: You were willing to stop [PSI Code 2.3.3] | U54: No full chapter yet. | V54: ▸ 1.6 Co-ordination — fine motor / handwriting, gross motor / PE skills full entry under 1. Observation in classroom, playground and clinic ▸ 5.1 Vision FULL ENTRY HERE ▸ 5.2 Hearing FULL ENTRY HERE ▸ 5.3 Medical condition or other diagnosis FULL ENTRY HERE | W54: Table 2 area 1 · Appendix 5 tagged Assessment · Appendix 7 observation · Table 3 tools and categories | X54: Equal Status Acts · Equal Status Acts 2000–2018 — reasonable accommodation · GDPR — lawful basis, minimisation | Y54: Year 1 — Becomes routine in disability settings in Year 2 and in high-risk contexts in Year 3.
A55: AREA | B55: 1. Assessment | D55: 10. Adapt standardised procedure and record the adaptation | E55: Referral area | F55: 5.1 Vision | G55: ON THE FORM — Section 5 | K55: =COUNTIF(Log!$E$3:$E$402,"5.1 Vision") | L55: =IF(COUNTIF(Log!$E$3:$E$402,"5.1 Vision")=0,"",SUMPRODUCT(MAX((Log!$E$3:$E$402="5.1 Vision")*Log!$A$3:$A$402))) | M55: DIAGNOSES ▸ Visual impairment Medical | N55: PRESENTATIONS WITH NO DIAGNOSIS ▸ Uncorrected refractive error Added — rule out before assessing literacy ▸ Visual fatigue in extended reading Added ▸ Access to print — font, size, contrast, position in room Added | O55: REFER TO ▸ Ophthalmology ▸ Visiting Teacher service ▸ CDNT ▸ GP ▸ Optometry ▸ NEPS ▸ Visiting Teacher | P55: — | Q55: ▸ Early Years / Pre-School (0–5) Vision screening history · Public Health Nurse records · never assess visually loaded tasks before vision is ruled out. | R55: ▸ School Age (6–12) Confirm date of last vision check before any literacy or non-verbal assessment · Visiting Teacher involvement · seating and print access. | S55: ▸ Adolescent (13–16) As above, plus exam access arrangements and the visual load of post-primary subjects. | T55: ▸ Young Adult (17–26) Access technology and DSA evidence. | U55: ▸ Special Setting (class or school) Environmental access audit. | AG55: Environmental Factors — Family, School, Community · Family dynamics (including CEC, adopted and CYP with SGOs) · Siblings, extended family, links and relationship to school and education · Family stressors · Financial stress · Housing · Home learning environment · Parental attitude to school/education · Trauma/significant life events · Adverse childhood events · Family views · Bereavements/relational losses · Key adults / members of staff (significant relationships both positive and negative in and out of school) and level of school commitment to child · Travel distance to school · School attendance · Child's views/preferences · School-parent relationship · Peer group dynamics · School learning environment · Access to interventions and support · Curriculum/exam boards · Teacher expectations · Teacher/staff understanding/knowledge · Attainment-based grouping · Influences in school and the local community · Other agency involvement — Police, YOT, CAMHS, Speech and Language Service, Fair Access, SENAT, Virtual School, SGO Advisor, Intensive Planning Team, Prevent, CSE, Early Years, School Nurse, Portage, Early Help, Social and Caring Services Health Services | AH55: Within-Child — Biological Factors · Family history including early development, physical development, medical conditions and diagnoses/difficulties · General health · Medication · Dietary needs · Sensory needs · Addictions e.g. smoking, drink, drugs | AI55: Within-Child — Cognitive Factors ASSESSABLE · Memory · Language · Executive functioning: including emotional and behavioural regulation/development · Attention and concentration · Visual spatial ability · Phonological processing · Processing speed · Non-verbal reasoning · Verbal ability (e.g. word problems, verbal presentation) · Logical reasoning ability · Literacy skills · Attainment OBSERVATION AND CONSULTATION · Signs of developmental trauma impacting on ability to participate in learning · Ability to problem-solve · Flexibility of thought and action · Self-awareness | AJ55: Within-Child — Affective Factors · Experience of developmental trauma · Confidence · Self-esteem · Emotional understanding and expression · Sense of enablement · Sense of self · Sense of belonging · Motivation (intrinsic or extrinsic) · Resiliency · Mood · Anxiety · Aspirations · Perseverance / determination · Sense of humour · Self-control · Social skills · Empathy | AK55: Within-Child — Behavioural Factors · Ability to develop and maintain friendships and relationships · Positive achievements · Care/concern for others, volunteering, helping · Dangerous or risk-taking behaviour · Verbal / physical abuse · Self-harm · Bullying · Truancy
A56: AREA | B56: 1. Assessment | D56: 10. Adapt standardised procedure and record the adaptation | E56: Referral area | F56: 5.2 Hearing | G56: ON THE FORM — Section 5 | K56: =COUNTIF(Log!$E$3:$E$402,"5.2 Hearing") | L56: =IF(COUNTIF(Log!$E$3:$E$402,"5.2 Hearing")=0,"",SUMPRODUCT(MAX((Log!$E$3:$E$402="5.2 Hearing")*Log!$A$3:$A$402))) | M56: DIAGNOSES ▸ Hearing impairment (mild, moderate, severe, profound; unilateral or bilateral) Medical ▸ Recurrent otitis media with effusion (glue ear) Medical | N56: PRESENTATIONS WITH NO DIAGNOSIS ▸ Listening in noise vs listening one-to-one Added ▸ Classroom acoustics and seating Added ▸ Hearing history during the years phonics was taught Added — glue ear at 5 shows up at 8 | O56: REFER TO ▸ Audiology ▸ Visiting Teacher service ▸ CDNT ▸ GP ▸ Audiology — common contributor to literacy difficulty ▸ NEPS ▸ Visiting Teacher | P56: — | Q56: ▸ Early Years / Pre-School (0–5) Newborn screening and PHN records · glue ear history · always establish before any language conclusion. | R56: ▸ School Age (6–12) Confirm audiology status before assessing language or literacy · a history of glue ear during infant classes is a live hypothesis for literacy difficulty. | S56: ▸ Adolescent (13–16) Audiology status · FM system use · acoustics in specialist rooms. | T56: ▸ Young Adult (17–26) Access technology and course arrangements. | U56: ▸ Special Setting (class or school) Acoustic environment and total communication approach. | AG56: Environmental Factors — Family, School, Community · Family dynamics (including CEC, adopted and CYP with SGOs) · Siblings, extended family, links and relationship to school and education · Family stressors · Financial stress · Housing · Home learning environment · Parental attitude to school/education · Trauma/significant life events · Adverse childhood events · Family views · Bereavements/relational losses · Key adults / members of staff (significant relationships both positive and negative in and out of school) and level of school commitment to child · Travel distance to school · School attendance · Child's views/preferences · School-parent relationship · Peer group dynamics · School learning environment · Access to interventions and support · Curriculum/exam boards · Teacher expectations · Teacher/staff understanding/knowledge · Attainment-based grouping · Influences in school and the local community · Other agency involvement — Police, YOT, CAMHS, Speech and Language Service, Fair Access, SENAT, Virtual School, SGO Advisor, Intensive Planning Team, Prevent, CSE, Early Years, School Nurse, Portage, Early Help, Social and Caring Services Health Services | AH56: Within-Child — Biological Factors · Family history including early development, physical development, medical conditions and diagnoses/difficulties · General health · Medication · Dietary needs · Sensory needs · Addictions e.g. smoking, drink, drugs | AI56: Within-Child — Cognitive Factors ASSESSABLE · Memory · Language · Executive functioning: including emotional and behavioural regulation/development · Attention and concentration · Visual spatial ability · Phonological processing · Processing speed · Non-verbal reasoning · Verbal ability (e.g. word problems, verbal presentation) · Logical reasoning ability · Literacy skills · Attainment OBSERVATION AND CONSULTATION · Signs of developmental trauma impacting on ability to participate in learning · Ability to problem-solve · Flexibility of thought and action · Self-awareness | AJ56: Within-Child — Affective Factors · Experience of developmental trauma · Confidence · Self-esteem · Emotional understanding and expression · Sense of enablement · Sense of self · Sense of belonging · Motivation (intrinsic or extrinsic) · Resiliency · Mood · Anxiety · Aspirations · Perseverance / determination · Sense of humour · Self-control · Social skills · Empathy | AK56: Within-Child — Behavioural Factors · Ability to develop and maintain friendships and relationships · Positive achievements · Care/concern for others, volunteering, helping · Dangerous or risk-taking behaviour · Verbal / physical abuse · Self-harm · Bullying · Truancy
